{"loss": -909.2079874674479, "accuracy": 0.2760416666666667, "time_this_iter_s": 10.799964666366577, "done": false, "timesteps_total": null, "episodes_total": null, "training_iteration": 1, "trial_id": "e71fd_00393", "experiment_id": "c943fdeaf340446482b3770e966ed732", "date": "2023-04-01_13-15-44", "timestamp": 1680347744, "time_total_s": 10.799964666366577, "pid": 1572373, "hostname": "cuda01", "node_ip": "172.29.16.1", "config": {"num_cont": 10, "lf": 0, "temperature": 0.01, "lr": 1e-05, "alpha": 20, "beta": 10, "seed": 2, "normalized": false, "batch_size": 32}, "time_since_restore": 10.799964666366577, "timesteps_since_restore": 0, "iterations_since_restore": 1, "warmup_time": 0.005432844161987305}
{"loss": -896.132080078125, "accuracy": 0.21354166666666666, "time_this_iter_s": 2.407898426055908, "done": false, "timesteps_total": null, "episodes_total": null, "training_iteration": 2, "trial_id": "e71fd_00393", "experiment_id": "c943fdeaf340446482b3770e966ed732", "date": "2023-04-01_13-15-47", "timestamp": 1680347747, "time_total_s": 13.207863092422485, "pid": 1572373, "hostname": "cuda01", "node_ip": "172.29.16.1", "config": {"num_cont": 10, "lf": 0, "temperature": 0.01, "lr": 1e-05, "alpha": 20, "beta": 10, "seed": 2, "normalized": false, "batch_size": 32}, "time_since_restore": 13.207863092422485, "timesteps_since_restore": 0, "iterations_since_restore": 2, "warmup_time": 0.005432844161987305}
{"loss": -871.9842732747396, "accuracy": 0.328125, "time_this_iter_s": 2.297049045562744, "done": false, "timesteps_total": null, "episodes_total": null, "training_iteration": 3, "trial_id": "e71fd_00393", "experiment_id": "c943fdeaf340446482b3770e966ed732", "date": "2023-04-01_13-15-49", "timestamp": 1680347749, "time_total_s": 15.50491213798523, "pid": 1572373, "hostname": "cuda01", "node_ip": "172.29.16.1", "config": {"num_cont": 10, "lf": 0, "temperature": 0.01, "lr": 1e-05, "alpha": 20, "beta": 10, "seed": 2, "normalized": false, "batch_size": 32}, "time_since_restore": 15.50491213798523, "timesteps_since_restore": 0, "iterations_since_restore": 3, "warmup_time": 0.005432844161987305}
{"loss": -809.0890401204427, "accuracy": 0.3385416666666667, "time_this_iter_s": 2.3213212490081787, "done": false, "timesteps_total": null, "episodes_total": null, "training_iteration": 4, "trial_id": "e71fd_00393", "experiment_id": "c943fdeaf340446482b3770e966ed732", "date": "2023-04-01_13-15-51", "timestamp": 1680347751, "time_total_s": 17.826233386993408, "pid": 1572373, "hostname": "cuda01", "node_ip": "172.29.16.1", "config": {"num_cont": 10, "lf": 0, "temperature": 0.01, "lr": 1e-05, "alpha": 20, "beta": 10, "seed": 2, "normalized": false, "batch_size": 32}, "time_since_restore": 17.826233386993408, "timesteps_since_restore": 0, "iterations_since_restore": 4, "warmup_time": 0.005432844161987305}
{"loss": -705.2256978352865, "accuracy": 0.3020833333333333, "time_this_iter_s": 2.414655923843384, "done": false, "timesteps_total": null, "episodes_total": null, "training_iteration": 5, "trial_id": "e71fd_00393", "experiment_id": "c943fdeaf340446482b3770e966ed732", "date": "2023-04-01_13-15-54", "timestamp": 1680347754, "time_total_s": 20.240889310836792, "pid": 1572373, "hostname": "cuda01", "node_ip": "172.29.16.1", "config": {"num_cont": 10, "lf": 0, "temperature": 0.01, "lr": 1e-05, "alpha": 20, "beta": 10, "seed": 2, "normalized": false, "batch_size": 32}, "time_since_restore": 20.240889310836792, "timesteps_since_restore": 0, "iterations_since_restore": 5, "warmup_time": 0.005432844161987305}
{"loss": -628.2988484700521, "accuracy": 0.25, "time_this_iter_s": 2.2146685123443604, "done": false, "timesteps_total": null, "episodes_total": null, "training_iteration": 6, "trial_id": "e71fd_00393", "experiment_id": "c943fdeaf340446482b3770e966ed732", "date": "2023-04-01_13-15-56", "timestamp": 1680347756, "time_total_s": 22.455557823181152, "pid": 1572373, "hostname": "cuda01", "node_ip": "172.29.16.1", "config": {"num_cont": 10, "lf": 0, "temperature": 0.01, "lr": 1e-05, "alpha": 20, "beta": 10, "seed": 2, "normalized": false, "batch_size": 32}, "time_since_restore": 22.455557823181152, "timesteps_since_restore": 0, "iterations_since_restore": 6, "warmup_time": 0.005432844161987305}
{"loss": -571.888173421224, "accuracy": 0.2604166666666667, "time_this_iter_s": 10.915227174758911, "done": false, "timesteps_total": null, "episodes_total": null, "training_iteration": 7, "trial_id": "e71fd_00393", "experiment_id": "c943fdeaf340446482b3770e966ed732", "date": "2023-04-01_13-16-07", "timestamp": 1680347767, "time_total_s": 33.37078499794006, "pid": 1572373, "hostname": "cuda01", "node_ip": "172.29.16.1", "config": {"num_cont": 10, "lf": 0, "temperature": 0.01, "lr": 1e-05, "alpha": 20, "beta": 10, "seed": 2, "normalized": false, "batch_size": 32}, "time_since_restore": 33.37078499794006, "timesteps_since_restore": 0, "iterations_since_restore": 7, "warmup_time": 0.005432844161987305}
{"loss": -532.562754313151, "accuracy": 0.3020833333333333, "time_this_iter_s": 2.255316972732544, "done": false, "timesteps_total": null, "episodes_total": null, "training_iteration": 8, "trial_id": "e71fd_00393", "experiment_id": "c943fdeaf340446482b3770e966ed732", "date": "2023-04-01_13-16-09", "timestamp": 1680347769, "time_total_s": 35.62610197067261, "pid": 1572373, "hostname": "cuda01", "node_ip": "172.29.16.1", "config": {"num_cont": 10, "lf": 0, "temperature": 0.01, "lr": 1e-05, "alpha": 20, "beta": 10, "seed": 2, "normalized": false, "batch_size": 32}, "time_since_restore": 35.62610197067261, "timesteps_since_restore": 0, "iterations_since_restore": 8, "warmup_time": 0.005432844161987305}
{"loss": -497.71050516764325, "accuracy": 0.3177083333333333, "time_this_iter_s": 2.263965129852295, "done": false, "timesteps_total": null, "episodes_total": null, "training_iteration": 9, "trial_id": "e71fd_00393", "experiment_id": "c943fdeaf340446482b3770e966ed732", "date": "2023-04-01_13-16-12", "timestamp": 1680347772, "time_total_s": 37.8900671005249, "pid": 1572373, "hostname": "cuda01", "node_ip": "172.29.16.1", "config": {"num_cont": 10, "lf": 0, "temperature": 0.01, "lr": 1e-05, "alpha": 20, "beta": 10, "seed": 2, "normalized": false, "batch_size": 32}, "time_since_restore": 37.8900671005249, "timesteps_since_restore": 0, "iterations_since_restore": 9, "warmup_time": 0.005432844161987305}
{"loss": -473.4629313151042, "accuracy": 0.25, "time_this_iter_s": 5.837943077087402, "done": true, "timesteps_total": null, "episodes_total": null, "training_iteration": 10, "trial_id": "e71fd_00393", "experiment_id": "c943fdeaf340446482b3770e966ed732", "date": "2023-04-01_13-16-17", "timestamp": 1680347777, "time_total_s": 43.728010177612305, "pid": 1572373, "hostname": "cuda01", "node_ip": "172.29.16.1", "config": {"num_cont": 10, "lf": 0, "temperature": 0.01, "lr": 1e-05, "alpha": 20, "beta": 10, "seed": 2, "normalized": false, "batch_size": 32}, "time_since_restore": 43.728010177612305, "timesteps_since_restore": 0, "iterations_since_restore": 10, "warmup_time": 0.005432844161987305}
