{"loss": -423.8738301595052, "accuracy": 0.3229166666666667, "time_this_iter_s": 10.435279607772827, "done": false, "timesteps_total": null, "episodes_total": null, "training_iteration": 1, "trial_id": "a0d9a_00169", "experiment_id": "7d987c86b1734058a7705e85cb01f23b", "date": "2023-03-31_17-34-23", "timestamp": 1680276863, "time_total_s": 10.435279607772827, "pid": 1356844, "hostname": "cuda01", "node_ip": "172.29.16.1", "config": {"num_cont": 50, "lf": 0, "temperature": 1, "lr": 0.001, "alpha": 200, "beta": 0.1, "seed": 4, "normalized": false, "batch_size": 32}, "time_since_restore": 10.435279607772827, "timesteps_since_restore": 0, "iterations_since_restore": 1, "warmup_time": 0.0044934749603271484}
{"loss": -395.89308675130206, "accuracy": 0.34375, "time_this_iter_s": 1.2607128620147705, "done": false, "timesteps_total": null, "episodes_total": null, "training_iteration": 2, "trial_id": "a0d9a_00169", "experiment_id": "7d987c86b1734058a7705e85cb01f23b", "date": "2023-03-31_17-34-24", "timestamp": 1680276864, "time_total_s": 11.695992469787598, "pid": 1356844, "hostname": "cuda01", "node_ip": "172.29.16.1", "config": {"num_cont": 50, "lf": 0, "temperature": 1, "lr": 0.001, "alpha": 200, "beta": 0.1, "seed": 4, "normalized": false, "batch_size": 32}, "time_since_restore": 11.695992469787598, "timesteps_since_restore": 0, "iterations_since_restore": 2, "warmup_time": 0.0044934749603271484}
{"loss": -387.01695760091144, "accuracy": 0.34375, "time_this_iter_s": 1.2031528949737549, "done": false, "timesteps_total": null, "episodes_total": null, "training_iteration": 3, "trial_id": "a0d9a_00169", "experiment_id": "7d987c86b1734058a7705e85cb01f23b", "date": "2023-03-31_17-34-25", "timestamp": 1680276865, "time_total_s": 12.899145364761353, "pid": 1356844, "hostname": "cuda01", "node_ip": "172.29.16.1", "config": {"num_cont": 50, "lf": 0, "temperature": 1, "lr": 0.001, "alpha": 200, "beta": 0.1, "seed": 4, "normalized": false, "batch_size": 32}, "time_since_restore": 12.899145364761353, "timesteps_since_restore": 0, "iterations_since_restore": 3, "warmup_time": 0.0044934749603271484}
{"loss": -383.18992106119794, "accuracy": 0.3645833333333333, "time_this_iter_s": 1.222224235534668, "done": false, "timesteps_total": null, "episodes_total": null, "training_iteration": 4, "trial_id": "a0d9a_00169", "experiment_id": "7d987c86b1734058a7705e85cb01f23b", "date": "2023-03-31_17-34-27", "timestamp": 1680276867, "time_total_s": 14.12136960029602, "pid": 1356844, "hostname": "cuda01", "node_ip": "172.29.16.1", "config": {"num_cont": 50, "lf": 0, "temperature": 1, "lr": 0.001, "alpha": 200, "beta": 0.1, "seed": 4, "normalized": false, "batch_size": 32}, "time_since_restore": 14.12136960029602, "timesteps_since_restore": 0, "iterations_since_restore": 4, "warmup_time": 0.0044934749603271484}
{"loss": -381.9095153808594, "accuracy": 0.3541666666666667, "time_this_iter_s": 1.2022480964660645, "done": false, "timesteps_total": null, "episodes_total": null, "training_iteration": 5, "trial_id": "a0d9a_00169", "experiment_id": "7d987c86b1734058a7705e85cb01f23b", "date": "2023-03-31_17-34-28", "timestamp": 1680276868, "time_total_s": 15.323617696762085, "pid": 1356844, "hostname": "cuda01", "node_ip": "172.29.16.1", "config": {"num_cont": 50, "lf": 0, "temperature": 1, "lr": 0.001, "alpha": 200, "beta": 0.1, "seed": 4, "normalized": false, "batch_size": 32}, "time_since_restore": 15.323617696762085, "timesteps_since_restore": 0, "iterations_since_restore": 5, "warmup_time": 0.0044934749603271484}
{"loss": -381.9663594563802, "accuracy": 0.3645833333333333, "time_this_iter_s": 1.205277442932129, "done": false, "timesteps_total": null, "episodes_total": null, "training_iteration": 6, "trial_id": "a0d9a_00169", "experiment_id": "7d987c86b1734058a7705e85cb01f23b", "date": "2023-03-31_17-34-29", "timestamp": 1680276869, "time_total_s": 16.528895139694214, "pid": 1356844, "hostname": "cuda01", "node_ip": "172.29.16.1", "config": {"num_cont": 50, "lf": 0, "temperature": 1, "lr": 0.001, "alpha": 200, "beta": 0.1, "seed": 4, "normalized": false, "batch_size": 32}, "time_since_restore": 16.528895139694214, "timesteps_since_restore": 0, "iterations_since_restore": 6, "warmup_time": 0.0044934749603271484}
{"loss": -383.3771158854167, "accuracy": 0.3229166666666667, "time_this_iter_s": 1.436152458190918, "done": false, "timesteps_total": null, "episodes_total": null, "training_iteration": 7, "trial_id": "a0d9a_00169", "experiment_id": "7d987c86b1734058a7705e85cb01f23b", "date": "2023-03-31_17-34-30", "timestamp": 1680276870, "time_total_s": 17.965047597885132, "pid": 1356844, "hostname": "cuda01", "node_ip": "172.29.16.1", "config": {"num_cont": 50, "lf": 0, "temperature": 1, "lr": 0.001, "alpha": 200, "beta": 0.1, "seed": 4, "normalized": false, "batch_size": 32}, "time_since_restore": 17.965047597885132, "timesteps_since_restore": 0, "iterations_since_restore": 7, "warmup_time": 0.0044934749603271484}
{"loss": -380.8330586751302, "accuracy": 0.34375, "time_this_iter_s": 1.3199272155761719, "done": false, "timesteps_total": null, "episodes_total": null, "training_iteration": 8, "trial_id": "a0d9a_00169", "experiment_id": "7d987c86b1734058a7705e85cb01f23b", "date": "2023-03-31_17-34-32", "timestamp": 1680276872, "time_total_s": 19.284974813461304, "pid": 1356844, "hostname": "cuda01", "node_ip": "172.29.16.1", "config": {"num_cont": 50, "lf": 0, "temperature": 1, "lr": 0.001, "alpha": 200, "beta": 0.1, "seed": 4, "normalized": false, "batch_size": 32}, "time_since_restore": 19.284974813461304, "timesteps_since_restore": 0, "iterations_since_restore": 8, "warmup_time": 0.0044934749603271484}
{"loss": -379.27573649088544, "accuracy": 0.3541666666666667, "time_this_iter_s": 1.3716208934783936, "done": false, "timesteps_total": null, "episodes_total": null, "training_iteration": 9, "trial_id": "a0d9a_00169", "experiment_id": "7d987c86b1734058a7705e85cb01f23b", "date": "2023-03-31_17-34-33", "timestamp": 1680276873, "time_total_s": 20.656595706939697, "pid": 1356844, "hostname": "cuda01", "node_ip": "172.29.16.1", "config": {"num_cont": 50, "lf": 0, "temperature": 1, "lr": 0.001, "alpha": 200, "beta": 0.1, "seed": 4, "normalized": false, "batch_size": 32}, "time_since_restore": 20.656595706939697, "timesteps_since_restore": 0, "iterations_since_restore": 9, "warmup_time": 0.0044934749603271484}
{"loss": -379.27381388346356, "accuracy": 0.3333333333333333, "time_this_iter_s": 1.374708890914917, "done": true, "timesteps_total": null, "episodes_total": null, "training_iteration": 10, "trial_id": "a0d9a_00169", "experiment_id": "7d987c86b1734058a7705e85cb01f23b", "date": "2023-03-31_17-34-34", "timestamp": 1680276874, "time_total_s": 22.031304597854614, "pid": 1356844, "hostname": "cuda01", "node_ip": "172.29.16.1", "config": {"num_cont": 50, "lf": 0, "temperature": 1, "lr": 0.001, "alpha": 200, "beta": 0.1, "seed": 4, "normalized": false, "batch_size": 32}, "time_since_restore": 22.031304597854614, "timesteps_since_restore": 0, "iterations_since_restore": 10, "warmup_time": 0.0044934749603271484}
