{"loss": -401.7497253417969, "accuracy": 0.22916666666666666, "time_this_iter_s": 12.264700889587402, "done": false, "timesteps_total": null, "episodes_total": null, "training_iteration": 1, "trial_id": "e71fd_00165", "experiment_id": "225a878e02964264afbe0d5b6b25e8a1", "date": "2023-04-01_12-42-43", "timestamp": 1680345763, "time_total_s": 12.264700889587402, "pid": 1555959, "hostname": "cuda01", "node_ip": "172.29.16.1", "config": {"num_cont": 50, "lf": 0, "temperature": 0.6, "lr": 0.001, "alpha": 500, "beta": 1, "seed": 27, "normalized": true, "batch_size": 32}, "time_since_restore": 12.264700889587402, "timesteps_since_restore": 0, "iterations_since_restore": 1, "warmup_time": 0.005032777786254883}
{"loss": -385.8325703938802, "accuracy": 0.1875, "time_this_iter_s": 2.3342998027801514, "done": false, "timesteps_total": null, "episodes_total": null, "training_iteration": 2, "trial_id": "e71fd_00165", "experiment_id": "225a878e02964264afbe0d5b6b25e8a1", "date": "2023-04-01_12-42-45", "timestamp": 1680345765, "time_total_s": 14.599000692367554, "pid": 1555959, "hostname": "cuda01", "node_ip": "172.29.16.1", "config": {"num_cont": 50, "lf": 0, "temperature": 0.6, "lr": 0.001, "alpha": 500, "beta": 1, "seed": 27, "normalized": true, "batch_size": 32}, "time_since_restore": 14.599000692367554, "timesteps_since_restore": 0, "iterations_since_restore": 2, "warmup_time": 0.005032777786254883}
{"loss": -382.2069600423177, "accuracy": 0.19270833333333334, "time_this_iter_s": 2.546081781387329, "done": false, "timesteps_total": null, "episodes_total": null, "training_iteration": 3, "trial_id": "e71fd_00165", "experiment_id": "225a878e02964264afbe0d5b6b25e8a1", "date": "2023-04-01_12-42-48", "timestamp": 1680345768, "time_total_s": 17.145082473754883, "pid": 1555959, "hostname": "cuda01", "node_ip": "172.29.16.1", "config": {"num_cont": 50, "lf": 0, "temperature": 0.6, "lr": 0.001, "alpha": 500, "beta": 1, "seed": 27, "normalized": true, "batch_size": 32}, "time_since_restore": 17.145082473754883, "timesteps_since_restore": 0, "iterations_since_restore": 3, "warmup_time": 0.005032777786254883}
{"loss": -380.86670939127606, "accuracy": 0.234375, "time_this_iter_s": 2.257405996322632, "done": false, "timesteps_total": null, "episodes_total": null, "training_iteration": 4, "trial_id": "e71fd_00165", "experiment_id": "225a878e02964264afbe0d5b6b25e8a1", "date": "2023-04-01_12-42-50", "timestamp": 1680345770, "time_total_s": 19.402488470077515, "pid": 1555959, "hostname": "cuda01", "node_ip": "172.29.16.1", "config": {"num_cont": 50, "lf": 0, "temperature": 0.6, "lr": 0.001, "alpha": 500, "beta": 1, "seed": 27, "normalized": true, "batch_size": 32}, "time_since_restore": 19.402488470077515, "timesteps_since_restore": 0, "iterations_since_restore": 4, "warmup_time": 0.005032777786254883}
{"loss": -380.0255940755208, "accuracy": 0.203125, "time_this_iter_s": 2.3751256465911865, "done": false, "timesteps_total": null, "episodes_total": null, "training_iteration": 5, "trial_id": "e71fd_00165", "experiment_id": "225a878e02964264afbe0d5b6b25e8a1", "date": "2023-04-01_12-42-52", "timestamp": 1680345772, "time_total_s": 21.7776141166687, "pid": 1555959, "hostname": "cuda01", "node_ip": "172.29.16.1", "config": {"num_cont": 50, "lf": 0, "temperature": 0.6, "lr": 0.001, "alpha": 500, "beta": 1, "seed": 27, "normalized": true, "batch_size": 32}, "time_since_restore": 21.7776141166687, "timesteps_since_restore": 0, "iterations_since_restore": 5, "warmup_time": 0.005032777786254883}
{"loss": -379.278076171875, "accuracy": 0.19270833333333334, "time_this_iter_s": 2.288433790206909, "done": false, "timesteps_total": null, "episodes_total": null, "training_iteration": 6, "trial_id": "e71fd_00165", "experiment_id": "225a878e02964264afbe0d5b6b25e8a1", "date": "2023-04-01_12-42-55", "timestamp": 1680345775, "time_total_s": 24.06604790687561, "pid": 1555959, "hostname": "cuda01", "node_ip": "172.29.16.1", "config": {"num_cont": 50, "lf": 0, "temperature": 0.6, "lr": 0.001, "alpha": 500, "beta": 1, "seed": 27, "normalized": true, "batch_size": 32}, "time_since_restore": 24.06604790687561, "timesteps_since_restore": 0, "iterations_since_restore": 6, "warmup_time": 0.005032777786254883}
{"loss": -379.4535166422526, "accuracy": 0.20833333333333334, "time_this_iter_s": 2.2320563793182373, "done": false, "timesteps_total": null, "episodes_total": null, "training_iteration": 7, "trial_id": "e71fd_00165", "experiment_id": "225a878e02964264afbe0d5b6b25e8a1", "date": "2023-04-01_12-42-57", "timestamp": 1680345777, "time_total_s": 26.298104286193848, "pid": 1555959, "hostname": "cuda01", "node_ip": "172.29.16.1", "config": {"num_cont": 50, "lf": 0, "temperature": 0.6, "lr": 0.001, "alpha": 500, "beta": 1, "seed": 27, "normalized": true, "batch_size": 32}, "time_since_restore": 26.298104286193848, "timesteps_since_restore": 0, "iterations_since_restore": 7, "warmup_time": 0.005032777786254883}
{"loss": -379.52630615234375, "accuracy": 0.21875, "time_this_iter_s": 2.400024175643921, "done": false, "timesteps_total": null, "episodes_total": null, "training_iteration": 8, "trial_id": "e71fd_00165", "experiment_id": "225a878e02964264afbe0d5b6b25e8a1", "date": "2023-04-01_12-42-59", "timestamp": 1680345779, "time_total_s": 28.69812846183777, "pid": 1555959, "hostname": "cuda01", "node_ip": "172.29.16.1", "config": {"num_cont": 50, "lf": 0, "temperature": 0.6, "lr": 0.001, "alpha": 500, "beta": 1, "seed": 27, "normalized": true, "batch_size": 32}, "time_since_restore": 28.69812846183777, "timesteps_since_restore": 0, "iterations_since_restore": 8, "warmup_time": 0.005032777786254883}
{"loss": -377.7723642985026, "accuracy": 0.20833333333333334, "time_this_iter_s": 2.157813787460327, "done": false, "timesteps_total": null, "episodes_total": null, "training_iteration": 9, "trial_id": "e71fd_00165", "experiment_id": "225a878e02964264afbe0d5b6b25e8a1", "date": "2023-04-01_12-43-01", "timestamp": 1680345781, "time_total_s": 30.855942249298096, "pid": 1555959, "hostname": "cuda01", "node_ip": "172.29.16.1", "config": {"num_cont": 50, "lf": 0, "temperature": 0.6, "lr": 0.001, "alpha": 500, "beta": 1, "seed": 27, "normalized": true, "batch_size": 32}, "time_since_restore": 30.855942249298096, "timesteps_since_restore": 0, "iterations_since_restore": 9, "warmup_time": 0.005032777786254883}
{"loss": -376.4498341878255, "accuracy": 0.24479166666666666, "time_this_iter_s": 2.196645498275757, "done": true, "timesteps_total": null, "episodes_total": null, "training_iteration": 10, "trial_id": "e71fd_00165", "experiment_id": "225a878e02964264afbe0d5b6b25e8a1", "date": "2023-04-01_12-43-04", "timestamp": 1680345784, "time_total_s": 33.05258774757385, "pid": 1555959, "hostname": "cuda01", "node_ip": "172.29.16.1", "config": {"num_cont": 50, "lf": 0, "temperature": 0.6, "lr": 0.001, "alpha": 500, "beta": 1, "seed": 27, "normalized": true, "batch_size": 32}, "time_since_restore": 33.05258774757385, "timesteps_since_restore": 0, "iterations_since_restore": 10, "warmup_time": 0.005032777786254883}
