{"loss": -1607.4867451985676, "accuracy": 0.20833333333333334, "time_this_iter_s": 9.817778587341309, "done": false, "timesteps_total": null, "episodes_total": null, "training_iteration": 1, "trial_id": "e71fd_00132", "experiment_id": "4e8d6334a08b457e8fb8dc9aaa090edd", "date": "2023-04-01_12-37-22", "timestamp": 1680345442, "time_total_s": 9.817778587341309, "pid": 1553513, "hostname": "cuda01", "node_ip": "172.29.16.1", "config": {"num_cont": 50, "lf": 0, "temperature": 1, "lr": 1e-05, "alpha": 200, "beta": 100, "seed": 27, "normalized": true, "batch_size": 16}, "time_since_restore": 9.817778587341309, "timesteps_since_restore": 0, "iterations_since_restore": 1, "warmup_time": 0.005235910415649414}
{"loss": -1548.4877115885417, "accuracy": 0.24479166666666666, "time_this_iter_s": 3.1598381996154785, "done": false, "timesteps_total": null, "episodes_total": null, "training_iteration": 2, "trial_id": "e71fd_00132", "experiment_id": "4e8d6334a08b457e8fb8dc9aaa090edd", "date": "2023-04-01_12-37-26", "timestamp": 1680345446, "time_total_s": 12.977616786956787, "pid": 1553513, "hostname": "cuda01", "node_ip": "172.29.16.1", "config": {"num_cont": 50, "lf": 0, "temperature": 1, "lr": 1e-05, "alpha": 200, "beta": 100, "seed": 27, "normalized": true, "batch_size": 16}, "time_since_restore": 12.977616786956787, "timesteps_since_restore": 0, "iterations_since_restore": 2, "warmup_time": 0.005235910415649414}
{"loss": -1388.7247619628906, "accuracy": 0.22916666666666666, "time_this_iter_s": 2.896531820297241, "done": false, "timesteps_total": null, "episodes_total": null, "training_iteration": 3, "trial_id": "e71fd_00132", "experiment_id": "4e8d6334a08b457e8fb8dc9aaa090edd", "date": "2023-04-01_12-37-28", "timestamp": 1680345448, "time_total_s": 15.874148607254028, "pid": 1553513, "hostname": "cuda01", "node_ip": "172.29.16.1", "config": {"num_cont": 50, "lf": 0, "temperature": 1, "lr": 1e-05, "alpha": 200, "beta": 100, "seed": 27, "normalized": true, "batch_size": 16}, "time_since_restore": 15.874148607254028, "timesteps_since_restore": 0, "iterations_since_restore": 3, "warmup_time": 0.005235910415649414}
{"loss": -1145.6768697102864, "accuracy": 0.22395833333333334, "time_this_iter_s": 2.9160268306732178, "done": false, "timesteps_total": null, "episodes_total": null, "training_iteration": 4, "trial_id": "e71fd_00132", "experiment_id": "4e8d6334a08b457e8fb8dc9aaa090edd", "date": "2023-04-01_12-37-31", "timestamp": 1680345451, "time_total_s": 18.790175437927246, "pid": 1553513, "hostname": "cuda01", "node_ip": "172.29.16.1", "config": {"num_cont": 50, "lf": 0, "temperature": 1, "lr": 1e-05, "alpha": 200, "beta": 100, "seed": 27, "normalized": true, "batch_size": 16}, "time_since_restore": 18.790175437927246, "timesteps_since_restore": 0, "iterations_since_restore": 4, "warmup_time": 0.005235910415649414}
{"loss": -978.1861623128256, "accuracy": 0.2604166666666667, "time_this_iter_s": 2.869345188140869, "done": false, "timesteps_total": null, "episodes_total": null, "training_iteration": 5, "trial_id": "e71fd_00132", "experiment_id": "4e8d6334a08b457e8fb8dc9aaa090edd", "date": "2023-04-01_12-37-34", "timestamp": 1680345454, "time_total_s": 21.659520626068115, "pid": 1553513, "hostname": "cuda01", "node_ip": "172.29.16.1", "config": {"num_cont": 50, "lf": 0, "temperature": 1, "lr": 1e-05, "alpha": 200, "beta": 100, "seed": 27, "normalized": true, "batch_size": 16}, "time_since_restore": 21.659520626068115, "timesteps_since_restore": 0, "iterations_since_restore": 5, "warmup_time": 0.005235910415649414}
{"loss": -864.2084757486979, "accuracy": 0.21875, "time_this_iter_s": 2.8978793621063232, "done": false, "timesteps_total": null, "episodes_total": null, "training_iteration": 6, "trial_id": "e71fd_00132", "experiment_id": "4e8d6334a08b457e8fb8dc9aaa090edd", "date": "2023-04-01_12-37-37", "timestamp": 1680345457, "time_total_s": 24.55739998817444, "pid": 1553513, "hostname": "cuda01", "node_ip": "172.29.16.1", "config": {"num_cont": 50, "lf": 0, "temperature": 1, "lr": 1e-05, "alpha": 200, "beta": 100, "seed": 27, "normalized": true, "batch_size": 16}, "time_since_restore": 24.55739998817444, "timesteps_since_restore": 0, "iterations_since_restore": 6, "warmup_time": 0.005235910415649414}
{"loss": -828.7155049641927, "accuracy": 0.23958333333333334, "time_this_iter_s": 2.8064379692077637, "done": false, "timesteps_total": null, "episodes_total": null, "training_iteration": 7, "trial_id": "e71fd_00132", "experiment_id": "4e8d6334a08b457e8fb8dc9aaa090edd", "date": "2023-04-01_12-37-40", "timestamp": 1680345460, "time_total_s": 27.363837957382202, "pid": 1553513, "hostname": "cuda01", "node_ip": "172.29.16.1", "config": {"num_cont": 50, "lf": 0, "temperature": 1, "lr": 1e-05, "alpha": 200, "beta": 100, "seed": 27, "normalized": true, "batch_size": 16}, "time_since_restore": 27.363837957382202, "timesteps_since_restore": 0, "iterations_since_restore": 7, "warmup_time": 0.005235910415649414}
{"loss": -812.542490641276, "accuracy": 0.22395833333333334, "time_this_iter_s": 2.9287757873535156, "done": false, "timesteps_total": null, "episodes_total": null, "training_iteration": 8, "trial_id": "e71fd_00132", "experiment_id": "4e8d6334a08b457e8fb8dc9aaa090edd", "date": "2023-04-01_12-37-43", "timestamp": 1680345463, "time_total_s": 30.292613744735718, "pid": 1553513, "hostname": "cuda01", "node_ip": "172.29.16.1", "config": {"num_cont": 50, "lf": 0, "temperature": 1, "lr": 1e-05, "alpha": 200, "beta": 100, "seed": 27, "normalized": true, "batch_size": 16}, "time_since_restore": 30.292613744735718, "timesteps_since_restore": 0, "iterations_since_restore": 8, "warmup_time": 0.005235910415649414}
{"loss": -801.1692454020182, "accuracy": 0.25, "time_this_iter_s": 2.8882968425750732, "done": false, "timesteps_total": null, "episodes_total": null, "training_iteration": 9, "trial_id": "e71fd_00132", "experiment_id": "4e8d6334a08b457e8fb8dc9aaa090edd", "date": "2023-04-01_12-37-46", "timestamp": 1680345466, "time_total_s": 33.18091058731079, "pid": 1553513, "hostname": "cuda01", "node_ip": "172.29.16.1", "config": {"num_cont": 50, "lf": 0, "temperature": 1, "lr": 1e-05, "alpha": 200, "beta": 100, "seed": 27, "normalized": true, "batch_size": 16}, "time_since_restore": 33.18091058731079, "timesteps_since_restore": 0, "iterations_since_restore": 9, "warmup_time": 0.005235910415649414}
{"loss": -794.3826751708984, "accuracy": 0.18229166666666666, "time_this_iter_s": 2.836888074874878, "done": true, "timesteps_total": null, "episodes_total": null, "training_iteration": 10, "trial_id": "e71fd_00132", "experiment_id": "4e8d6334a08b457e8fb8dc9aaa090edd", "date": "2023-04-01_12-37-49", "timestamp": 1680345469, "time_total_s": 36.01779866218567, "pid": 1553513, "hostname": "cuda01", "node_ip": "172.29.16.1", "config": {"num_cont": 50, "lf": 0, "temperature": 1, "lr": 1e-05, "alpha": 200, "beta": 100, "seed": 27, "normalized": true, "batch_size": 16}, "time_since_restore": 36.01779866218567, "timesteps_since_restore": 0, "iterations_since_restore": 10, "warmup_time": 0.005235910415649414}
