{"loss": -440.46807861328125, "accuracy": 0.546875, "time_this_iter_s": 9.979995489120483, "done": false, "timesteps_total": null, "episodes_total": null, "training_iteration": 1, "trial_id": "a0d9a_00357", "experiment_id": "a84899bb77fd4dadab8ef404ea39a6c3", "date": "2023-03-31_17-57-09", "timestamp": 1680278229, "time_total_s": 9.979995489120483, "pid": 1369926, "hostname": "cuda01", "node_ip": "172.29.16.1", "config": {"num_cont": 10, "lf": 0, "temperature": 1, "lr": 1e-06, "alpha": 200, "beta": 4, "seed": 27, "normalized": false, "batch_size": 64}, "time_since_restore": 9.979995489120483, "timesteps_since_restore": 0, "iterations_since_restore": 1, "warmup_time": 0.0058171749114990234}
{"loss": -440.4488220214844, "accuracy": 0.4375, "time_this_iter_s": 1.4391210079193115, "done": false, "timesteps_total": null, "episodes_total": null, "training_iteration": 2, "trial_id": "a0d9a_00357", "experiment_id": "a84899bb77fd4dadab8ef404ea39a6c3", "date": "2023-03-31_17-57-11", "timestamp": 1680278231, "time_total_s": 11.419116497039795, "pid": 1369926, "hostname": "cuda01", "node_ip": "172.29.16.1", "config": {"num_cont": 10, "lf": 0, "temperature": 1, "lr": 1e-06, "alpha": 200, "beta": 4, "seed": 27, "normalized": false, "batch_size": 64}, "time_since_restore": 11.419116497039795, "timesteps_since_restore": 0, "iterations_since_restore": 2, "warmup_time": 0.0058171749114990234}
{"loss": -440.4090270996094, "accuracy": 0.640625, "time_this_iter_s": 1.106658697128296, "done": false, "timesteps_total": null, "episodes_total": null, "training_iteration": 3, "trial_id": "a0d9a_00357", "experiment_id": "a84899bb77fd4dadab8ef404ea39a6c3", "date": "2023-03-31_17-57-12", "timestamp": 1680278232, "time_total_s": 12.52577519416809, "pid": 1369926, "hostname": "cuda01", "node_ip": "172.29.16.1", "config": {"num_cont": 10, "lf": 0, "temperature": 1, "lr": 1e-06, "alpha": 200, "beta": 4, "seed": 27, "normalized": false, "batch_size": 64}, "time_since_restore": 12.52577519416809, "timesteps_since_restore": 0, "iterations_since_restore": 3, "warmup_time": 0.0058171749114990234}
{"loss": -440.31158447265625, "accuracy": 0.390625, "time_this_iter_s": 1.074295997619629, "done": false, "timesteps_total": null, "episodes_total": null, "training_iteration": 4, "trial_id": "a0d9a_00357", "experiment_id": "a84899bb77fd4dadab8ef404ea39a6c3", "date": "2023-03-31_17-57-13", "timestamp": 1680278233, "time_total_s": 13.60007119178772, "pid": 1369926, "hostname": "cuda01", "node_ip": "172.29.16.1", "config": {"num_cont": 10, "lf": 0, "temperature": 1, "lr": 1e-06, "alpha": 200, "beta": 4, "seed": 27, "normalized": false, "batch_size": 64}, "time_since_restore": 13.60007119178772, "timesteps_since_restore": 0, "iterations_since_restore": 4, "warmup_time": 0.0058171749114990234}
{"loss": -440.169921875, "accuracy": 0.453125, "time_this_iter_s": 1.0533347129821777, "done": false, "timesteps_total": null, "episodes_total": null, "training_iteration": 5, "trial_id": "a0d9a_00357", "experiment_id": "a84899bb77fd4dadab8ef404ea39a6c3", "date": "2023-03-31_17-57-14", "timestamp": 1680278234, "time_total_s": 14.653405904769897, "pid": 1369926, "hostname": "cuda01", "node_ip": "172.29.16.1", "config": {"num_cont": 10, "lf": 0, "temperature": 1, "lr": 1e-06, "alpha": 200, "beta": 4, "seed": 27, "normalized": false, "batch_size": 64}, "time_since_restore": 14.653405904769897, "timesteps_since_restore": 0, "iterations_since_restore": 5, "warmup_time": 0.0058171749114990234}
{"loss": -440.0991516113281, "accuracy": 0.59375, "time_this_iter_s": 1.0549561977386475, "done": false, "timesteps_total": null, "episodes_total": null, "training_iteration": 6, "trial_id": "a0d9a_00357", "experiment_id": "a84899bb77fd4dadab8ef404ea39a6c3", "date": "2023-03-31_17-57-15", "timestamp": 1680278235, "time_total_s": 15.708362102508545, "pid": 1369926, "hostname": "cuda01", "node_ip": "172.29.16.1", "config": {"num_cont": 10, "lf": 0, "temperature": 1, "lr": 1e-06, "alpha": 200, "beta": 4, "seed": 27, "normalized": false, "batch_size": 64}, "time_since_restore": 15.708362102508545, "timesteps_since_restore": 0, "iterations_since_restore": 6, "warmup_time": 0.0058171749114990234}
{"loss": -440.2067565917969, "accuracy": 0.515625, "time_this_iter_s": 1.2695398330688477, "done": false, "timesteps_total": null, "episodes_total": null, "training_iteration": 7, "trial_id": "a0d9a_00357", "experiment_id": "a84899bb77fd4dadab8ef404ea39a6c3", "date": "2023-03-31_17-57-16", "timestamp": 1680278236, "time_total_s": 16.977901935577393, "pid": 1369926, "hostname": "cuda01", "node_ip": "172.29.16.1", "config": {"num_cont": 10, "lf": 0, "temperature": 1, "lr": 1e-06, "alpha": 200, "beta": 4, "seed": 27, "normalized": false, "batch_size": 64}, "time_since_restore": 16.977901935577393, "timesteps_since_restore": 0, "iterations_since_restore": 7, "warmup_time": 0.0058171749114990234}
{"loss": -440.0995178222656, "accuracy": 0.46875, "time_this_iter_s": 1.286205768585205, "done": false, "timesteps_total": null, "episodes_total": null, "training_iteration": 8, "trial_id": "a0d9a_00357", "experiment_id": "a84899bb77fd4dadab8ef404ea39a6c3", "date": "2023-03-31_17-57-17", "timestamp": 1680278237, "time_total_s": 18.264107704162598, "pid": 1369926, "hostname": "cuda01", "node_ip": "172.29.16.1", "config": {"num_cont": 10, "lf": 0, "temperature": 1, "lr": 1e-06, "alpha": 200, "beta": 4, "seed": 27, "normalized": false, "batch_size": 64}, "time_since_restore": 18.264107704162598, "timesteps_since_restore": 0, "iterations_since_restore": 8, "warmup_time": 0.0058171749114990234}
{"loss": -440.0821838378906, "accuracy": 0.53125, "time_this_iter_s": 1.1443891525268555, "done": false, "timesteps_total": null, "episodes_total": null, "training_iteration": 9, "trial_id": "a0d9a_00357", "experiment_id": "a84899bb77fd4dadab8ef404ea39a6c3", "date": "2023-03-31_17-57-19", "timestamp": 1680278239, "time_total_s": 19.408496856689453, "pid": 1369926, "hostname": "cuda01", "node_ip": "172.29.16.1", "config": {"num_cont": 10, "lf": 0, "temperature": 1, "lr": 1e-06, "alpha": 200, "beta": 4, "seed": 27, "normalized": false, "batch_size": 64}, "time_since_restore": 19.408496856689453, "timesteps_since_restore": 0, "iterations_since_restore": 9, "warmup_time": 0.0058171749114990234}
{"loss": -439.95233154296875, "accuracy": 0.59375, "time_this_iter_s": 1.0981287956237793, "done": false, "timesteps_total": null, "episodes_total": null, "training_iteration": 10, "trial_id": "a0d9a_00357", "experiment_id": "a84899bb77fd4dadab8ef404ea39a6c3", "date": "2023-03-31_17-57-20", "timestamp": 1680278240, "time_total_s": 20.506625652313232, "pid": 1369926, "hostname": "cuda01", "node_ip": "172.29.16.1", "config": {"num_cont": 10, "lf": 0, "temperature": 1, "lr": 1e-06, "alpha": 200, "beta": 4, "seed": 27, "normalized": false, "batch_size": 64}, "time_since_restore": 20.506625652313232, "timesteps_since_restore": 0, "iterations_since_restore": 10, "warmup_time": 0.0058171749114990234}
{"loss": -439.89630126953125, "accuracy": 0.4375, "time_this_iter_s": 1.108738660812378, "done": false, "timesteps_total": null, "episodes_total": null, "training_iteration": 11, "trial_id": "a0d9a_00357", "experiment_id": "a84899bb77fd4dadab8ef404ea39a6c3", "date": "2023-03-31_17-57-21", "timestamp": 1680278241, "time_total_s": 21.61536431312561, "pid": 1369926, "hostname": "cuda01", "node_ip": "172.29.16.1", "config": {"num_cont": 10, "lf": 0, "temperature": 1, "lr": 1e-06, "alpha": 200, "beta": 4, "seed": 27, "normalized": false, "batch_size": 64}, "time_since_restore": 21.61536431312561, "timesteps_since_restore": 0, "iterations_since_restore": 11, "warmup_time": 0.0058171749114990234}
{"loss": -439.90093994140625, "accuracy": 0.5, "time_this_iter_s": 1.2477293014526367, "done": false, "timesteps_total": null, "episodes_total": null, "training_iteration": 12, "trial_id": "a0d9a_00357", "experiment_id": "a84899bb77fd4dadab8ef404ea39a6c3", "date": "2023-03-31_17-57-22", "timestamp": 1680278242, "time_total_s": 22.863093614578247, "pid": 1369926, "hostname": "cuda01", "node_ip": "172.29.16.1", "config": {"num_cont": 10, "lf": 0, "temperature": 1, "lr": 1e-06, "alpha": 200, "beta": 4, "seed": 27, "normalized": false, "batch_size": 64}, "time_since_restore": 22.863093614578247, "timesteps_since_restore": 0, "iterations_since_restore": 12, "warmup_time": 0.0058171749114990234}
{"loss": -439.9072570800781, "accuracy": 0.4375, "time_this_iter_s": 1.0854523181915283, "done": false, "timesteps_total": null, "episodes_total": null, "training_iteration": 13, "trial_id": "a0d9a_00357", "experiment_id": "a84899bb77fd4dadab8ef404ea39a6c3", "date": "2023-03-31_17-57-23", "timestamp": 1680278243, "time_total_s": 23.948545932769775, "pid": 1369926, "hostname": "cuda01", "node_ip": "172.29.16.1", "config": {"num_cont": 10, "lf": 0, "temperature": 1, "lr": 1e-06, "alpha": 200, "beta": 4, "seed": 27, "normalized": false, "batch_size": 64}, "time_since_restore": 23.948545932769775, "timesteps_since_restore": 0, "iterations_since_restore": 13, "warmup_time": 0.0058171749114990234}
{"loss": -439.697021484375, "accuracy": 0.546875, "time_this_iter_s": 1.0641136169433594, "done": false, "timesteps_total": null, "episodes_total": null, "training_iteration": 14, "trial_id": "a0d9a_00357", "experiment_id": "a84899bb77fd4dadab8ef404ea39a6c3", "date": "2023-03-31_17-57-24", "timestamp": 1680278244, "time_total_s": 25.012659549713135, "pid": 1369926, "hostname": "cuda01", "node_ip": "172.29.16.1", "config": {"num_cont": 10, "lf": 0, "temperature": 1, "lr": 1e-06, "alpha": 200, "beta": 4, "seed": 27, "normalized": false, "batch_size": 64}, "time_since_restore": 25.012659549713135, "timesteps_since_restore": 0, "iterations_since_restore": 14, "warmup_time": 0.0058171749114990234}
{"loss": -439.948486328125, "accuracy": 0.53125, "time_this_iter_s": 1.0184221267700195, "done": false, "timesteps_total": null, "episodes_total": null, "training_iteration": 15, "trial_id": "a0d9a_00357", "experiment_id": "a84899bb77fd4dadab8ef404ea39a6c3", "date": "2023-03-31_17-57-25", "timestamp": 1680278245, "time_total_s": 26.031081676483154, "pid": 1369926, "hostname": "cuda01", "node_ip": "172.29.16.1", "config": {"num_cont": 10, "lf": 0, "temperature": 1, "lr": 1e-06, "alpha": 200, "beta": 4, "seed": 27, "normalized": false, "batch_size": 64}, "time_since_restore": 26.031081676483154, "timesteps_since_restore": 0, "iterations_since_restore": 15, "warmup_time": 0.0058171749114990234}
{"loss": -439.6842041015625, "accuracy": 0.5625, "time_this_iter_s": 1.0104968547821045, "done": false, "timesteps_total": null, "episodes_total": null, "training_iteration": 16, "trial_id": "a0d9a_00357", "experiment_id": "a84899bb77fd4dadab8ef404ea39a6c3", "date": "2023-03-31_17-57-26", "timestamp": 1680278246, "time_total_s": 27.04157853126526, "pid": 1369926, "hostname": "cuda01", "node_ip": "172.29.16.1", "config": {"num_cont": 10, "lf": 0, "temperature": 1, "lr": 1e-06, "alpha": 200, "beta": 4, "seed": 27, "normalized": false, "batch_size": 64}, "time_since_restore": 27.04157853126526, "timesteps_since_restore": 0, "iterations_since_restore": 16, "warmup_time": 0.0058171749114990234}
{"loss": -439.6358947753906, "accuracy": 0.421875, "time_this_iter_s": 1.2230398654937744, "done": false, "timesteps_total": null, "episodes_total": null, "training_iteration": 17, "trial_id": "a0d9a_00357", "experiment_id": "a84899bb77fd4dadab8ef404ea39a6c3", "date": "2023-03-31_17-57-27", "timestamp": 1680278247, "time_total_s": 28.264618396759033, "pid": 1369926, "hostname": "cuda01", "node_ip": "172.29.16.1", "config": {"num_cont": 10, "lf": 0, "temperature": 1, "lr": 1e-06, "alpha": 200, "beta": 4, "seed": 27, "normalized": false, "batch_size": 64}, "time_since_restore": 28.264618396759033, "timesteps_since_restore": 0, "iterations_since_restore": 17, "warmup_time": 0.0058171749114990234}
{"loss": -439.5901184082031, "accuracy": 0.640625, "time_this_iter_s": 1.0122957229614258, "done": false, "timesteps_total": null, "episodes_total": null, "training_iteration": 18, "trial_id": "a0d9a_00357", "experiment_id": "a84899bb77fd4dadab8ef404ea39a6c3", "date": "2023-03-31_17-57-28", "timestamp": 1680278248, "time_total_s": 29.27691411972046, "pid": 1369926, "hostname": "cuda01", "node_ip": "172.29.16.1", "config": {"num_cont": 10, "lf": 0, "temperature": 1, "lr": 1e-06, "alpha": 200, "beta": 4, "seed": 27, "normalized": false, "batch_size": 64}, "time_since_restore": 29.27691411972046, "timesteps_since_restore": 0, "iterations_since_restore": 18, "warmup_time": 0.0058171749114990234}
{"loss": -439.5206604003906, "accuracy": 0.484375, "time_this_iter_s": 1.1158061027526855, "done": false, "timesteps_total": null, "episodes_total": null, "training_iteration": 19, "trial_id": "a0d9a_00357", "experiment_id": "a84899bb77fd4dadab8ef404ea39a6c3", "date": "2023-03-31_17-57-30", "timestamp": 1680278250, "time_total_s": 30.392720222473145, "pid": 1369926, "hostname": "cuda01", "node_ip": "172.29.16.1", "config": {"num_cont": 10, "lf": 0, "temperature": 1, "lr": 1e-06, "alpha": 200, "beta": 4, "seed": 27, "normalized": false, "batch_size": 64}, "time_since_restore": 30.392720222473145, "timesteps_since_restore": 0, "iterations_since_restore": 19, "warmup_time": 0.0058171749114990234}
{"loss": -439.4669494628906, "accuracy": 0.515625, "time_this_iter_s": 1.0964617729187012, "done": false, "timesteps_total": null, "episodes_total": null, "training_iteration": 20, "trial_id": "a0d9a_00357", "experiment_id": "a84899bb77fd4dadab8ef404ea39a6c3", "date": "2023-03-31_17-57-31", "timestamp": 1680278251, "time_total_s": 31.489181995391846, "pid": 1369926, "hostname": "cuda01", "node_ip": "172.29.16.1", "config": {"num_cont": 10, "lf": 0, "temperature": 1, "lr": 1e-06, "alpha": 200, "beta": 4, "seed": 27, "normalized": false, "batch_size": 64}, "time_since_restore": 31.489181995391846, "timesteps_since_restore": 0, "iterations_since_restore": 20, "warmup_time": 0.0058171749114990234}
{"loss": -439.3336181640625, "accuracy": 0.53125, "time_this_iter_s": 1.0924904346466064, "done": false, "timesteps_total": null, "episodes_total": null, "training_iteration": 21, "trial_id": "a0d9a_00357", "experiment_id": "a84899bb77fd4dadab8ef404ea39a6c3", "date": "2023-03-31_17-57-32", "timestamp": 1680278252, "time_total_s": 32.58167243003845, "pid": 1369926, "hostname": "cuda01", "node_ip": "172.29.16.1", "config": {"num_cont": 10, "lf": 0, "temperature": 1, "lr": 1e-06, "alpha": 200, "beta": 4, "seed": 27, "normalized": false, "batch_size": 64}, "time_since_restore": 32.58167243003845, "timesteps_since_restore": 0, "iterations_since_restore": 21, "warmup_time": 0.0058171749114990234}
{"loss": -439.50909423828125, "accuracy": 0.453125, "time_this_iter_s": 1.1955111026763916, "done": false, "timesteps_total": null, "episodes_total": null, "training_iteration": 22, "trial_id": "a0d9a_00357", "experiment_id": "a84899bb77fd4dadab8ef404ea39a6c3", "date": "2023-03-31_17-57-33", "timestamp": 1680278253, "time_total_s": 33.777183532714844, "pid": 1369926, "hostname": "cuda01", "node_ip": "172.29.16.1", "config": {"num_cont": 10, "lf": 0, "temperature": 1, "lr": 1e-06, "alpha": 200, "beta": 4, "seed": 27, "normalized": false, "batch_size": 64}, "time_since_restore": 33.777183532714844, "timesteps_since_restore": 0, "iterations_since_restore": 22, "warmup_time": 0.0058171749114990234}
{"loss": -439.306396484375, "accuracy": 0.515625, "time_this_iter_s": 1.0632233619689941, "done": false, "timesteps_total": null, "episodes_total": null, "training_iteration": 23, "trial_id": "a0d9a_00357", "experiment_id": "a84899bb77fd4dadab8ef404ea39a6c3", "date": "2023-03-31_17-57-34", "timestamp": 1680278254, "time_total_s": 34.84040689468384, "pid": 1369926, "hostname": "cuda01", "node_ip": "172.29.16.1", "config": {"num_cont": 10, "lf": 0, "temperature": 1, "lr": 1e-06, "alpha": 200, "beta": 4, "seed": 27, "normalized": false, "batch_size": 64}, "time_since_restore": 34.84040689468384, "timesteps_since_restore": 0, "iterations_since_restore": 23, "warmup_time": 0.0058171749114990234}
{"loss": -439.3255920410156, "accuracy": 0.4375, "time_this_iter_s": 1.0614514350891113, "done": false, "timesteps_total": null, "episodes_total": null, "training_iteration": 24, "trial_id": "a0d9a_00357", "experiment_id": "a84899bb77fd4dadab8ef404ea39a6c3", "date": "2023-03-31_17-57-35", "timestamp": 1680278255, "time_total_s": 35.90185832977295, "pid": 1369926, "hostname": "cuda01", "node_ip": "172.29.16.1", "config": {"num_cont": 10, "lf": 0, "temperature": 1, "lr": 1e-06, "alpha": 200, "beta": 4, "seed": 27, "normalized": false, "batch_size": 64}, "time_since_restore": 35.90185832977295, "timesteps_since_restore": 0, "iterations_since_restore": 24, "warmup_time": 0.0058171749114990234}
{"loss": -439.0548095703125, "accuracy": 0.515625, "time_this_iter_s": 1.0818426609039307, "done": false, "timesteps_total": null, "episodes_total": null, "training_iteration": 25, "trial_id": "a0d9a_00357", "experiment_id": "a84899bb77fd4dadab8ef404ea39a6c3", "date": "2023-03-31_17-57-36", "timestamp": 1680278256, "time_total_s": 36.98370099067688, "pid": 1369926, "hostname": "cuda01", "node_ip": "172.29.16.1", "config": {"num_cont": 10, "lf": 0, "temperature": 1, "lr": 1e-06, "alpha": 200, "beta": 4, "seed": 27, "normalized": false, "batch_size": 64}, "time_since_restore": 36.98370099067688, "timesteps_since_restore": 0, "iterations_since_restore": 25, "warmup_time": 0.0058171749114990234}
{"loss": -439.052734375, "accuracy": 0.53125, "time_this_iter_s": 1.0722615718841553, "done": false, "timesteps_total": null, "episodes_total": null, "training_iteration": 26, "trial_id": "a0d9a_00357", "experiment_id": "a84899bb77fd4dadab8ef404ea39a6c3", "date": "2023-03-31_17-57-37", "timestamp": 1680278257, "time_total_s": 38.055962562561035, "pid": 1369926, "hostname": "cuda01", "node_ip": "172.29.16.1", "config": {"num_cont": 10, "lf": 0, "temperature": 1, "lr": 1e-06, "alpha": 200, "beta": 4, "seed": 27, "normalized": false, "batch_size": 64}, "time_since_restore": 38.055962562561035, "timesteps_since_restore": 0, "iterations_since_restore": 26, "warmup_time": 0.0058171749114990234}
{"loss": -438.989990234375, "accuracy": 0.578125, "time_this_iter_s": 1.1917965412139893, "done": false, "timesteps_total": null, "episodes_total": null, "training_iteration": 27, "trial_id": "a0d9a_00357", "experiment_id": "a84899bb77fd4dadab8ef404ea39a6c3", "date": "2023-03-31_17-57-38", "timestamp": 1680278258, "time_total_s": 39.247759103775024, "pid": 1369926, "hostname": "cuda01", "node_ip": "172.29.16.1", "config": {"num_cont": 10, "lf": 0, "temperature": 1, "lr": 1e-06, "alpha": 200, "beta": 4, "seed": 27, "normalized": false, "batch_size": 64}, "time_since_restore": 39.247759103775024, "timesteps_since_restore": 0, "iterations_since_restore": 27, "warmup_time": 0.0058171749114990234}
{"loss": -438.8569641113281, "accuracy": 0.40625, "time_this_iter_s": 1.0688529014587402, "done": false, "timesteps_total": null, "episodes_total": null, "training_iteration": 28, "trial_id": "a0d9a_00357", "experiment_id": "a84899bb77fd4dadab8ef404ea39a6c3", "date": "2023-03-31_17-57-39", "timestamp": 1680278259, "time_total_s": 40.316612005233765, "pid": 1369926, "hostname": "cuda01", "node_ip": "172.29.16.1", "config": {"num_cont": 10, "lf": 0, "temperature": 1, "lr": 1e-06, "alpha": 200, "beta": 4, "seed": 27, "normalized": false, "batch_size": 64}, "time_since_restore": 40.316612005233765, "timesteps_since_restore": 0, "iterations_since_restore": 28, "warmup_time": 0.0058171749114990234}
{"loss": -438.9417419433594, "accuracy": 0.578125, "time_this_iter_s": 1.0209269523620605, "done": false, "timesteps_total": null, "episodes_total": null, "training_iteration": 29, "trial_id": "a0d9a_00357", "experiment_id": "a84899bb77fd4dadab8ef404ea39a6c3", "date": "2023-03-31_17-57-40", "timestamp": 1680278260, "time_total_s": 41.337538957595825, "pid": 1369926, "hostname": "cuda01", "node_ip": "172.29.16.1", "config": {"num_cont": 10, "lf": 0, "temperature": 1, "lr": 1e-06, "alpha": 200, "beta": 4, "seed": 27, "normalized": false, "batch_size": 64}, "time_since_restore": 41.337538957595825, "timesteps_since_restore": 0, "iterations_since_restore": 29, "warmup_time": 0.0058171749114990234}
{"loss": -438.8529052734375, "accuracy": 0.640625, "time_this_iter_s": 1.075223445892334, "done": false, "timesteps_total": null, "episodes_total": null, "training_iteration": 30, "trial_id": "a0d9a_00357", "experiment_id": "a84899bb77fd4dadab8ef404ea39a6c3", "date": "2023-03-31_17-57-42", "timestamp": 1680278262, "time_total_s": 42.41276240348816, "pid": 1369926, "hostname": "cuda01", "node_ip": "172.29.16.1", "config": {"num_cont": 10, "lf": 0, "temperature": 1, "lr": 1e-06, "alpha": 200, "beta": 4, "seed": 27, "normalized": false, "batch_size": 64}, "time_since_restore": 42.41276240348816, "timesteps_since_restore": 0, "iterations_since_restore": 30, "warmup_time": 0.0058171749114990234}
{"loss": -438.95013427734375, "accuracy": 0.375, "time_this_iter_s": 1.0407443046569824, "done": false, "timesteps_total": null, "episodes_total": null, "training_iteration": 31, "trial_id": "a0d9a_00357", "experiment_id": "a84899bb77fd4dadab8ef404ea39a6c3", "date": "2023-03-31_17-57-43", "timestamp": 1680278263, "time_total_s": 43.45350670814514, "pid": 1369926, "hostname": "cuda01", "node_ip": "172.29.16.1", "config": {"num_cont": 10, "lf": 0, "temperature": 1, "lr": 1e-06, "alpha": 200, "beta": 4, "seed": 27, "normalized": false, "batch_size": 64}, "time_since_restore": 43.45350670814514, "timesteps_since_restore": 0, "iterations_since_restore": 31, "warmup_time": 0.0058171749114990234}
{"loss": -438.7864685058594, "accuracy": 0.46875, "time_this_iter_s": 1.1712453365325928, "done": false, "timesteps_total": null, "episodes_total": null, "training_iteration": 32, "trial_id": "a0d9a_00357", "experiment_id": "a84899bb77fd4dadab8ef404ea39a6c3", "date": "2023-03-31_17-57-44", "timestamp": 1680278264, "time_total_s": 44.624752044677734, "pid": 1369926, "hostname": "cuda01", "node_ip": "172.29.16.1", "config": {"num_cont": 10, "lf": 0, "temperature": 1, "lr": 1e-06, "alpha": 200, "beta": 4, "seed": 27, "normalized": false, "batch_size": 64}, "time_since_restore": 44.624752044677734, "timesteps_since_restore": 0, "iterations_since_restore": 32, "warmup_time": 0.0058171749114990234}
{"loss": -438.42919921875, "accuracy": 0.421875, "time_this_iter_s": 1.058950662612915, "done": false, "timesteps_total": null, "episodes_total": null, "training_iteration": 33, "trial_id": "a0d9a_00357", "experiment_id": "a84899bb77fd4dadab8ef404ea39a6c3", "date": "2023-03-31_17-57-45", "timestamp": 1680278265, "time_total_s": 45.68370270729065, "pid": 1369926, "hostname": "cuda01", "node_ip": "172.29.16.1", "config": {"num_cont": 10, "lf": 0, "temperature": 1, "lr": 1e-06, "alpha": 200, "beta": 4, "seed": 27, "normalized": false, "batch_size": 64}, "time_since_restore": 45.68370270729065, "timesteps_since_restore": 0, "iterations_since_restore": 33, "warmup_time": 0.0058171749114990234}
{"loss": -438.65362548828125, "accuracy": 0.421875, "time_this_iter_s": 1.0375385284423828, "done": false, "timesteps_total": null, "episodes_total": null, "training_iteration": 34, "trial_id": "a0d9a_00357", "experiment_id": "a84899bb77fd4dadab8ef404ea39a6c3", "date": "2023-03-31_17-57-46", "timestamp": 1680278266, "time_total_s": 46.72124123573303, "pid": 1369926, "hostname": "cuda01", "node_ip": "172.29.16.1", "config": {"num_cont": 10, "lf": 0, "temperature": 1, "lr": 1e-06, "alpha": 200, "beta": 4, "seed": 27, "normalized": false, "batch_size": 64}, "time_since_restore": 46.72124123573303, "timesteps_since_restore": 0, "iterations_since_restore": 34, "warmup_time": 0.0058171749114990234}
{"loss": -438.4665832519531, "accuracy": 0.484375, "time_this_iter_s": 1.0416746139526367, "done": false, "timesteps_total": null, "episodes_total": null, "training_iteration": 35, "trial_id": "a0d9a_00357", "experiment_id": "a84899bb77fd4dadab8ef404ea39a6c3", "date": "2023-03-31_17-57-47", "timestamp": 1680278267, "time_total_s": 47.76291584968567, "pid": 1369926, "hostname": "cuda01", "node_ip": "172.29.16.1", "config": {"num_cont": 10, "lf": 0, "temperature": 1, "lr": 1e-06, "alpha": 200, "beta": 4, "seed": 27, "normalized": false, "batch_size": 64}, "time_since_restore": 47.76291584968567, "timesteps_since_restore": 0, "iterations_since_restore": 35, "warmup_time": 0.0058171749114990234}
{"loss": -438.23370361328125, "accuracy": 0.484375, "time_this_iter_s": 1.075441598892212, "done": false, "timesteps_total": null, "episodes_total": null, "training_iteration": 36, "trial_id": "a0d9a_00357", "experiment_id": "a84899bb77fd4dadab8ef404ea39a6c3", "date": "2023-03-31_17-57-48", "timestamp": 1680278268, "time_total_s": 48.83835744857788, "pid": 1369926, "hostname": "cuda01", "node_ip": "172.29.16.1", "config": {"num_cont": 10, "lf": 0, "temperature": 1, "lr": 1e-06, "alpha": 200, "beta": 4, "seed": 27, "normalized": false, "batch_size": 64}, "time_since_restore": 48.83835744857788, "timesteps_since_restore": 0, "iterations_since_restore": 36, "warmup_time": 0.0058171749114990234}
{"loss": -438.36578369140625, "accuracy": 0.515625, "time_this_iter_s": 1.1859004497528076, "done": false, "timesteps_total": null, "episodes_total": null, "training_iteration": 37, "trial_id": "a0d9a_00357", "experiment_id": "a84899bb77fd4dadab8ef404ea39a6c3", "date": "2023-03-31_17-57-49", "timestamp": 1680278269, "time_total_s": 50.02425789833069, "pid": 1369926, "hostname": "cuda01", "node_ip": "172.29.16.1", "config": {"num_cont": 10, "lf": 0, "temperature": 1, "lr": 1e-06, "alpha": 200, "beta": 4, "seed": 27, "normalized": false, "batch_size": 64}, "time_since_restore": 50.02425789833069, "timesteps_since_restore": 0, "iterations_since_restore": 37, "warmup_time": 0.0058171749114990234}
{"loss": -438.1626281738281, "accuracy": 0.484375, "time_this_iter_s": 1.0272440910339355, "done": false, "timesteps_total": null, "episodes_total": null, "training_iteration": 38, "trial_id": "a0d9a_00357", "experiment_id": "a84899bb77fd4dadab8ef404ea39a6c3", "date": "2023-03-31_17-57-50", "timestamp": 1680278270, "time_total_s": 51.051501989364624, "pid": 1369926, "hostname": "cuda01", "node_ip": "172.29.16.1", "config": {"num_cont": 10, "lf": 0, "temperature": 1, "lr": 1e-06, "alpha": 200, "beta": 4, "seed": 27, "normalized": false, "batch_size": 64}, "time_since_restore": 51.051501989364624, "timesteps_since_restore": 0, "iterations_since_restore": 38, "warmup_time": 0.0058171749114990234}
{"loss": -438.221923828125, "accuracy": 0.546875, "time_this_iter_s": 1.0091845989227295, "done": false, "timesteps_total": null, "episodes_total": null, "training_iteration": 39, "trial_id": "a0d9a_00357", "experiment_id": "a84899bb77fd4dadab8ef404ea39a6c3", "date": "2023-03-31_17-57-51", "timestamp": 1680278271, "time_total_s": 52.06068658828735, "pid": 1369926, "hostname": "cuda01", "node_ip": "172.29.16.1", "config": {"num_cont": 10, "lf": 0, "temperature": 1, "lr": 1e-06, "alpha": 200, "beta": 4, "seed": 27, "normalized": false, "batch_size": 64}, "time_since_restore": 52.06068658828735, "timesteps_since_restore": 0, "iterations_since_restore": 39, "warmup_time": 0.0058171749114990234}
{"loss": -438.0774230957031, "accuracy": 0.515625, "time_this_iter_s": 1.0384902954101562, "done": false, "timesteps_total": null, "episodes_total": null, "training_iteration": 40, "trial_id": "a0d9a_00357", "experiment_id": "a84899bb77fd4dadab8ef404ea39a6c3", "date": "2023-03-31_17-57-52", "timestamp": 1680278272, "time_total_s": 53.09917688369751, "pid": 1369926, "hostname": "cuda01", "node_ip": "172.29.16.1", "config": {"num_cont": 10, "lf": 0, "temperature": 1, "lr": 1e-06, "alpha": 200, "beta": 4, "seed": 27, "normalized": false, "batch_size": 64}, "time_since_restore": 53.09917688369751, "timesteps_since_restore": 0, "iterations_since_restore": 40, "warmup_time": 0.0058171749114990234}
{"loss": -438.14483642578125, "accuracy": 0.484375, "time_this_iter_s": 1.1365370750427246, "done": false, "timesteps_total": null, "episodes_total": null, "training_iteration": 41, "trial_id": "a0d9a_00357", "experiment_id": "a84899bb77fd4dadab8ef404ea39a6c3", "date": "2023-03-31_17-57-53", "timestamp": 1680278273, "time_total_s": 54.235713958740234, "pid": 1369926, "hostname": "cuda01", "node_ip": "172.29.16.1", "config": {"num_cont": 10, "lf": 0, "temperature": 1, "lr": 1e-06, "alpha": 200, "beta": 4, "seed": 27, "normalized": false, "batch_size": 64}, "time_since_restore": 54.235713958740234, "timesteps_since_restore": 0, "iterations_since_restore": 41, "warmup_time": 0.0058171749114990234}
{"loss": -438.02008056640625, "accuracy": 0.59375, "time_this_iter_s": 1.1943995952606201, "done": false, "timesteps_total": null, "episodes_total": null, "training_iteration": 42, "trial_id": "a0d9a_00357", "experiment_id": "a84899bb77fd4dadab8ef404ea39a6c3", "date": "2023-03-31_17-57-55", "timestamp": 1680278275, "time_total_s": 55.430113554000854, "pid": 1369926, "hostname": "cuda01", "node_ip": "172.29.16.1", "config": {"num_cont": 10, "lf": 0, "temperature": 1, "lr": 1e-06, "alpha": 200, "beta": 4, "seed": 27, "normalized": false, "batch_size": 64}, "time_since_restore": 55.430113554000854, "timesteps_since_restore": 0, "iterations_since_restore": 42, "warmup_time": 0.0058171749114990234}
{"loss": -438.00146484375, "accuracy": 0.421875, "time_this_iter_s": 1.039017915725708, "done": false, "timesteps_total": null, "episodes_total": null, "training_iteration": 43, "trial_id": "a0d9a_00357", "experiment_id": "a84899bb77fd4dadab8ef404ea39a6c3", "date": "2023-03-31_17-57-56", "timestamp": 1680278276, "time_total_s": 56.46913146972656, "pid": 1369926, "hostname": "cuda01", "node_ip": "172.29.16.1", "config": {"num_cont": 10, "lf": 0, "temperature": 1, "lr": 1e-06, "alpha": 200, "beta": 4, "seed": 27, "normalized": false, "batch_size": 64}, "time_since_restore": 56.46913146972656, "timesteps_since_restore": 0, "iterations_since_restore": 43, "warmup_time": 0.0058171749114990234}
{"loss": -437.923828125, "accuracy": 0.40625, "time_this_iter_s": 1.0847949981689453, "done": false, "timesteps_total": null, "episodes_total": null, "training_iteration": 44, "trial_id": "a0d9a_00357", "experiment_id": "a84899bb77fd4dadab8ef404ea39a6c3", "date": "2023-03-31_17-57-57", "timestamp": 1680278277, "time_total_s": 57.55392646789551, "pid": 1369926, "hostname": "cuda01", "node_ip": "172.29.16.1", "config": {"num_cont": 10, "lf": 0, "temperature": 1, "lr": 1e-06, "alpha": 200, "beta": 4, "seed": 27, "normalized": false, "batch_size": 64}, "time_since_restore": 57.55392646789551, "timesteps_since_restore": 0, "iterations_since_restore": 44, "warmup_time": 0.0058171749114990234}
{"loss": -437.9339904785156, "accuracy": 0.453125, "time_this_iter_s": 1.0557899475097656, "done": false, "timesteps_total": null, "episodes_total": null, "training_iteration": 45, "trial_id": "a0d9a_00357", "experiment_id": "a84899bb77fd4dadab8ef404ea39a6c3", "date": "2023-03-31_17-57-58", "timestamp": 1680278278, "time_total_s": 58.60971641540527, "pid": 1369926, "hostname": "cuda01", "node_ip": "172.29.16.1", "config": {"num_cont": 10, "lf": 0, "temperature": 1, "lr": 1e-06, "alpha": 200, "beta": 4, "seed": 27, "normalized": false, "batch_size": 64}, "time_since_restore": 58.60971641540527, "timesteps_since_restore": 0, "iterations_since_restore": 45, "warmup_time": 0.0058171749114990234}
{"loss": -437.7424011230469, "accuracy": 0.640625, "time_this_iter_s": 1.0416877269744873, "done": false, "timesteps_total": null, "episodes_total": null, "training_iteration": 46, "trial_id": "a0d9a_00357", "experiment_id": "a84899bb77fd4dadab8ef404ea39a6c3", "date": "2023-03-31_17-57-59", "timestamp": 1680278279, "time_total_s": 59.65140414237976, "pid": 1369926, "hostname": "cuda01", "node_ip": "172.29.16.1", "config": {"num_cont": 10, "lf": 0, "temperature": 1, "lr": 1e-06, "alpha": 200, "beta": 4, "seed": 27, "normalized": false, "batch_size": 64}, "time_since_restore": 59.65140414237976, "timesteps_since_restore": 0, "iterations_since_restore": 46, "warmup_time": 0.0058171749114990234}
{"loss": -437.6822509765625, "accuracy": 0.5, "time_this_iter_s": 1.1799721717834473, "done": false, "timesteps_total": null, "episodes_total": null, "training_iteration": 47, "trial_id": "a0d9a_00357", "experiment_id": "a84899bb77fd4dadab8ef404ea39a6c3", "date": "2023-03-31_17-58-00", "timestamp": 1680278280, "time_total_s": 60.83137631416321, "pid": 1369926, "hostname": "cuda01", "node_ip": "172.29.16.1", "config": {"num_cont": 10, "lf": 0, "temperature": 1, "lr": 1e-06, "alpha": 200, "beta": 4, "seed": 27, "normalized": false, "batch_size": 64}, "time_since_restore": 60.83137631416321, "timesteps_since_restore": 0, "iterations_since_restore": 47, "warmup_time": 0.0058171749114990234}
{"loss": -437.7331848144531, "accuracy": 0.46875, "time_this_iter_s": 1.042978048324585, "done": false, "timesteps_total": null, "episodes_total": null, "training_iteration": 48, "trial_id": "a0d9a_00357", "experiment_id": "a84899bb77fd4dadab8ef404ea39a6c3", "date": "2023-03-31_17-58-01", "timestamp": 1680278281, "time_total_s": 61.87435436248779, "pid": 1369926, "hostname": "cuda01", "node_ip": "172.29.16.1", "config": {"num_cont": 10, "lf": 0, "temperature": 1, "lr": 1e-06, "alpha": 200, "beta": 4, "seed": 27, "normalized": false, "batch_size": 64}, "time_since_restore": 61.87435436248779, "timesteps_since_restore": 0, "iterations_since_restore": 48, "warmup_time": 0.0058171749114990234}
{"loss": -437.51904296875, "accuracy": 0.515625, "time_this_iter_s": 1.0319280624389648, "done": false, "timesteps_total": null, "episodes_total": null, "training_iteration": 49, "trial_id": "a0d9a_00357", "experiment_id": "a84899bb77fd4dadab8ef404ea39a6c3", "date": "2023-03-31_17-58-02", "timestamp": 1680278282, "time_total_s": 62.90628242492676, "pid": 1369926, "hostname": "cuda01", "node_ip": "172.29.16.1", "config": {"num_cont": 10, "lf": 0, "temperature": 1, "lr": 1e-06, "alpha": 200, "beta": 4, "seed": 27, "normalized": false, "batch_size": 64}, "time_since_restore": 62.90628242492676, "timesteps_since_restore": 0, "iterations_since_restore": 49, "warmup_time": 0.0058171749114990234}
{"loss": -437.22943115234375, "accuracy": 0.53125, "time_this_iter_s": 1.0804331302642822, "done": false, "timesteps_total": null, "episodes_total": null, "training_iteration": 50, "trial_id": "a0d9a_00357", "experiment_id": "a84899bb77fd4dadab8ef404ea39a6c3", "date": "2023-03-31_17-58-03", "timestamp": 1680278283, "time_total_s": 63.98671555519104, "pid": 1369926, "hostname": "cuda01", "node_ip": "172.29.16.1", "config": {"num_cont": 10, "lf": 0, "temperature": 1, "lr": 1e-06, "alpha": 200, "beta": 4, "seed": 27, "normalized": false, "batch_size": 64}, "time_since_restore": 63.98671555519104, "timesteps_since_restore": 0, "iterations_since_restore": 50, "warmup_time": 0.0058171749114990234}
{"loss": -437.28582763671875, "accuracy": 0.515625, "time_this_iter_s": 1.0307395458221436, "done": false, "timesteps_total": null, "episodes_total": null, "training_iteration": 51, "trial_id": "a0d9a_00357", "experiment_id": "a84899bb77fd4dadab8ef404ea39a6c3", "date": "2023-03-31_17-58-04", "timestamp": 1680278284, "time_total_s": 65.01745510101318, "pid": 1369926, "hostname": "cuda01", "node_ip": "172.29.16.1", "config": {"num_cont": 10, "lf": 0, "temperature": 1, "lr": 1e-06, "alpha": 200, "beta": 4, "seed": 27, "normalized": false, "batch_size": 64}, "time_since_restore": 65.01745510101318, "timesteps_since_restore": 0, "iterations_since_restore": 51, "warmup_time": 0.0058171749114990234}
{"loss": -437.23114013671875, "accuracy": 0.546875, "time_this_iter_s": 1.177342414855957, "done": false, "timesteps_total": null, "episodes_total": null, "training_iteration": 52, "trial_id": "a0d9a_00357", "experiment_id": "a84899bb77fd4dadab8ef404ea39a6c3", "date": "2023-03-31_17-58-05", "timestamp": 1680278285, "time_total_s": 66.19479751586914, "pid": 1369926, "hostname": "cuda01", "node_ip": "172.29.16.1", "config": {"num_cont": 10, "lf": 0, "temperature": 1, "lr": 1e-06, "alpha": 200, "beta": 4, "seed": 27, "normalized": false, "batch_size": 64}, "time_since_restore": 66.19479751586914, "timesteps_since_restore": 0, "iterations_since_restore": 52, "warmup_time": 0.0058171749114990234}
{"loss": -437.10308837890625, "accuracy": 0.53125, "time_this_iter_s": 1.0471446514129639, "done": false, "timesteps_total": null, "episodes_total": null, "training_iteration": 53, "trial_id": "a0d9a_00357", "experiment_id": "a84899bb77fd4dadab8ef404ea39a6c3", "date": "2023-03-31_17-58-06", "timestamp": 1680278286, "time_total_s": 67.2419421672821, "pid": 1369926, "hostname": "cuda01", "node_ip": "172.29.16.1", "config": {"num_cont": 10, "lf": 0, "temperature": 1, "lr": 1e-06, "alpha": 200, "beta": 4, "seed": 27, "normalized": false, "batch_size": 64}, "time_since_restore": 67.2419421672821, "timesteps_since_restore": 0, "iterations_since_restore": 53, "warmup_time": 0.0058171749114990234}
{"loss": -437.17169189453125, "accuracy": 0.484375, "time_this_iter_s": 1.1584446430206299, "done": false, "timesteps_total": null, "episodes_total": null, "training_iteration": 54, "trial_id": "a0d9a_00357", "experiment_id": "a84899bb77fd4dadab8ef404ea39a6c3", "date": "2023-03-31_17-58-08", "timestamp": 1680278288, "time_total_s": 68.40038681030273, "pid": 1369926, "hostname": "cuda01", "node_ip": "172.29.16.1", "config": {"num_cont": 10, "lf": 0, "temperature": 1, "lr": 1e-06, "alpha": 200, "beta": 4, "seed": 27, "normalized": false, "batch_size": 64}, "time_since_restore": 68.40038681030273, "timesteps_since_restore": 0, "iterations_since_restore": 54, "warmup_time": 0.0058171749114990234}
{"loss": -437.0439147949219, "accuracy": 0.578125, "time_this_iter_s": 1.274458408355713, "done": false, "timesteps_total": null, "episodes_total": null, "training_iteration": 55, "trial_id": "a0d9a_00357", "experiment_id": "a84899bb77fd4dadab8ef404ea39a6c3", "date": "2023-03-31_17-58-09", "timestamp": 1680278289, "time_total_s": 69.67484521865845, "pid": 1369926, "hostname": "cuda01", "node_ip": "172.29.16.1", "config": {"num_cont": 10, "lf": 0, "temperature": 1, "lr": 1e-06, "alpha": 200, "beta": 4, "seed": 27, "normalized": false, "batch_size": 64}, "time_since_restore": 69.67484521865845, "timesteps_since_restore": 0, "iterations_since_restore": 55, "warmup_time": 0.0058171749114990234}
{"loss": -436.82666015625, "accuracy": 0.5625, "time_this_iter_s": 1.0268664360046387, "done": false, "timesteps_total": null, "episodes_total": null, "training_iteration": 56, "trial_id": "a0d9a_00357", "experiment_id": "a84899bb77fd4dadab8ef404ea39a6c3", "date": "2023-03-31_17-58-10", "timestamp": 1680278290, "time_total_s": 70.70171165466309, "pid": 1369926, "hostname": "cuda01", "node_ip": "172.29.16.1", "config": {"num_cont": 10, "lf": 0, "temperature": 1, "lr": 1e-06, "alpha": 200, "beta": 4, "seed": 27, "normalized": false, "batch_size": 64}, "time_since_restore": 70.70171165466309, "timesteps_since_restore": 0, "iterations_since_restore": 56, "warmup_time": 0.0058171749114990234}
{"loss": -436.88043212890625, "accuracy": 0.53125, "time_this_iter_s": 1.1586036682128906, "done": false, "timesteps_total": null, "episodes_total": null, "training_iteration": 57, "trial_id": "a0d9a_00357", "experiment_id": "a84899bb77fd4dadab8ef404ea39a6c3", "date": "2023-03-31_17-58-11", "timestamp": 1680278291, "time_total_s": 71.86031532287598, "pid": 1369926, "hostname": "cuda01", "node_ip": "172.29.16.1", "config": {"num_cont": 10, "lf": 0, "temperature": 1, "lr": 1e-06, "alpha": 200, "beta": 4, "seed": 27, "normalized": false, "batch_size": 64}, "time_since_restore": 71.86031532287598, "timesteps_since_restore": 0, "iterations_since_restore": 57, "warmup_time": 0.0058171749114990234}
{"loss": -436.5942077636719, "accuracy": 0.53125, "time_this_iter_s": 1.0295498371124268, "done": false, "timesteps_total": null, "episodes_total": null, "training_iteration": 58, "trial_id": "a0d9a_00357", "experiment_id": "a84899bb77fd4dadab8ef404ea39a6c3", "date": "2023-03-31_17-58-12", "timestamp": 1680278292, "time_total_s": 72.8898651599884, "pid": 1369926, "hostname": "cuda01", "node_ip": "172.29.16.1", "config": {"num_cont": 10, "lf": 0, "temperature": 1, "lr": 1e-06, "alpha": 200, "beta": 4, "seed": 27, "normalized": false, "batch_size": 64}, "time_since_restore": 72.8898651599884, "timesteps_since_restore": 0, "iterations_since_restore": 58, "warmup_time": 0.0058171749114990234}
{"loss": -436.4380187988281, "accuracy": 0.4375, "time_this_iter_s": 6.7736310958862305, "done": false, "timesteps_total": null, "episodes_total": null, "training_iteration": 59, "trial_id": "a0d9a_00357", "experiment_id": "a84899bb77fd4dadab8ef404ea39a6c3", "date": "2023-03-31_17-58-19", "timestamp": 1680278299, "time_total_s": 79.66349625587463, "pid": 1369926, "hostname": "cuda01", "node_ip": "172.29.16.1", "config": {"num_cont": 10, "lf": 0, "temperature": 1, "lr": 1e-06, "alpha": 200, "beta": 4, "seed": 27, "normalized": false, "batch_size": 64}, "time_since_restore": 79.66349625587463, "timesteps_since_restore": 0, "iterations_since_restore": 59, "warmup_time": 0.0058171749114990234}
{"loss": -436.3948669433594, "accuracy": 0.46875, "time_this_iter_s": 1.0266282558441162, "done": false, "timesteps_total": null, "episodes_total": null, "training_iteration": 60, "trial_id": "a0d9a_00357", "experiment_id": "a84899bb77fd4dadab8ef404ea39a6c3", "date": "2023-03-31_17-58-20", "timestamp": 1680278300, "time_total_s": 80.69012451171875, "pid": 1369926, "hostname": "cuda01", "node_ip": "172.29.16.1", "config": {"num_cont": 10, "lf": 0, "temperature": 1, "lr": 1e-06, "alpha": 200, "beta": 4, "seed": 27, "normalized": false, "batch_size": 64}, "time_since_restore": 80.69012451171875, "timesteps_since_restore": 0, "iterations_since_restore": 60, "warmup_time": 0.0058171749114990234}
{"loss": -436.42388916015625, "accuracy": 0.53125, "time_this_iter_s": 1.0302019119262695, "done": false, "timesteps_total": null, "episodes_total": null, "training_iteration": 61, "trial_id": "a0d9a_00357", "experiment_id": "a84899bb77fd4dadab8ef404ea39a6c3", "date": "2023-03-31_17-58-21", "timestamp": 1680278301, "time_total_s": 81.72032642364502, "pid": 1369926, "hostname": "cuda01", "node_ip": "172.29.16.1", "config": {"num_cont": 10, "lf": 0, "temperature": 1, "lr": 1e-06, "alpha": 200, "beta": 4, "seed": 27, "normalized": false, "batch_size": 64}, "time_since_restore": 81.72032642364502, "timesteps_since_restore": 0, "iterations_since_restore": 61, "warmup_time": 0.0058171749114990234}
{"loss": -436.2876892089844, "accuracy": 0.5, "time_this_iter_s": 1.0319273471832275, "done": false, "timesteps_total": null, "episodes_total": null, "training_iteration": 62, "trial_id": "a0d9a_00357", "experiment_id": "a84899bb77fd4dadab8ef404ea39a6c3", "date": "2023-03-31_17-58-22", "timestamp": 1680278302, "time_total_s": 82.75225377082825, "pid": 1369926, "hostname": "cuda01", "node_ip": "172.29.16.1", "config": {"num_cont": 10, "lf": 0, "temperature": 1, "lr": 1e-06, "alpha": 200, "beta": 4, "seed": 27, "normalized": false, "batch_size": 64}, "time_since_restore": 82.75225377082825, "timesteps_since_restore": 0, "iterations_since_restore": 62, "warmup_time": 0.0058171749114990234}
{"loss": -436.1300354003906, "accuracy": 0.484375, "time_this_iter_s": 1.000866413116455, "done": false, "timesteps_total": null, "episodes_total": null, "training_iteration": 63, "trial_id": "a0d9a_00357", "experiment_id": "a84899bb77fd4dadab8ef404ea39a6c3", "date": "2023-03-31_17-58-23", "timestamp": 1680278303, "time_total_s": 83.7531201839447, "pid": 1369926, "hostname": "cuda01", "node_ip": "172.29.16.1", "config": {"num_cont": 10, "lf": 0, "temperature": 1, "lr": 1e-06, "alpha": 200, "beta": 4, "seed": 27, "normalized": false, "batch_size": 64}, "time_since_restore": 83.7531201839447, "timesteps_since_restore": 0, "iterations_since_restore": 63, "warmup_time": 0.0058171749114990234}
{"loss": -435.9695739746094, "accuracy": 0.515625, "time_this_iter_s": 1.2060718536376953, "done": false, "timesteps_total": null, "episodes_total": null, "training_iteration": 64, "trial_id": "a0d9a_00357", "experiment_id": "a84899bb77fd4dadab8ef404ea39a6c3", "date": "2023-03-31_17-58-24", "timestamp": 1680278304, "time_total_s": 84.9591920375824, "pid": 1369926, "hostname": "cuda01", "node_ip": "172.29.16.1", "config": {"num_cont": 10, "lf": 0, "temperature": 1, "lr": 1e-06, "alpha": 200, "beta": 4, "seed": 27, "normalized": false, "batch_size": 64}, "time_since_restore": 84.9591920375824, "timesteps_since_restore": 0, "iterations_since_restore": 64, "warmup_time": 0.0058171749114990234}
{"loss": -435.8919372558594, "accuracy": 0.53125, "time_this_iter_s": 1.0112617015838623, "done": false, "timesteps_total": null, "episodes_total": null, "training_iteration": 65, "trial_id": "a0d9a_00357", "experiment_id": "a84899bb77fd4dadab8ef404ea39a6c3", "date": "2023-03-31_17-58-25", "timestamp": 1680278305, "time_total_s": 85.97045373916626, "pid": 1369926, "hostname": "cuda01", "node_ip": "172.29.16.1", "config": {"num_cont": 10, "lf": 0, "temperature": 1, "lr": 1e-06, "alpha": 200, "beta": 4, "seed": 27, "normalized": false, "batch_size": 64}, "time_since_restore": 85.97045373916626, "timesteps_since_restore": 0, "iterations_since_restore": 65, "warmup_time": 0.0058171749114990234}
{"loss": -435.7818908691406, "accuracy": 0.59375, "time_this_iter_s": 1.0099658966064453, "done": false, "timesteps_total": null, "episodes_total": null, "training_iteration": 66, "trial_id": "a0d9a_00357", "experiment_id": "a84899bb77fd4dadab8ef404ea39a6c3", "date": "2023-03-31_17-58-26", "timestamp": 1680278306, "time_total_s": 86.9804196357727, "pid": 1369926, "hostname": "cuda01", "node_ip": "172.29.16.1", "config": {"num_cont": 10, "lf": 0, "temperature": 1, "lr": 1e-06, "alpha": 200, "beta": 4, "seed": 27, "normalized": false, "batch_size": 64}, "time_since_restore": 86.9804196357727, "timesteps_since_restore": 0, "iterations_since_restore": 66, "warmup_time": 0.0058171749114990234}
{"loss": -435.612548828125, "accuracy": 0.59375, "time_this_iter_s": 1.0366261005401611, "done": false, "timesteps_total": null, "episodes_total": null, "training_iteration": 67, "trial_id": "a0d9a_00357", "experiment_id": "a84899bb77fd4dadab8ef404ea39a6c3", "date": "2023-03-31_17-58-27", "timestamp": 1680278307, "time_total_s": 88.01704573631287, "pid": 1369926, "hostname": "cuda01", "node_ip": "172.29.16.1", "config": {"num_cont": 10, "lf": 0, "temperature": 1, "lr": 1e-06, "alpha": 200, "beta": 4, "seed": 27, "normalized": false, "batch_size": 64}, "time_since_restore": 88.01704573631287, "timesteps_since_restore": 0, "iterations_since_restore": 67, "warmup_time": 0.0058171749114990234}
{"loss": -435.4926452636719, "accuracy": 0.5, "time_this_iter_s": 1.063302755355835, "done": false, "timesteps_total": null, "episodes_total": null, "training_iteration": 68, "trial_id": "a0d9a_00357", "experiment_id": "a84899bb77fd4dadab8ef404ea39a6c3", "date": "2023-03-31_17-58-28", "timestamp": 1680278308, "time_total_s": 89.0803484916687, "pid": 1369926, "hostname": "cuda01", "node_ip": "172.29.16.1", "config": {"num_cont": 10, "lf": 0, "temperature": 1, "lr": 1e-06, "alpha": 200, "beta": 4, "seed": 27, "normalized": false, "batch_size": 64}, "time_since_restore": 89.0803484916687, "timesteps_since_restore": 0, "iterations_since_restore": 68, "warmup_time": 0.0058171749114990234}
{"loss": -435.2635803222656, "accuracy": 0.53125, "time_this_iter_s": 1.1935899257659912, "done": false, "timesteps_total": null, "episodes_total": null, "training_iteration": 69, "trial_id": "a0d9a_00357", "experiment_id": "a84899bb77fd4dadab8ef404ea39a6c3", "date": "2023-03-31_17-58-29", "timestamp": 1680278309, "time_total_s": 90.27393841743469, "pid": 1369926, "hostname": "cuda01", "node_ip": "172.29.16.1", "config": {"num_cont": 10, "lf": 0, "temperature": 1, "lr": 1e-06, "alpha": 200, "beta": 4, "seed": 27, "normalized": false, "batch_size": 64}, "time_since_restore": 90.27393841743469, "timesteps_since_restore": 0, "iterations_since_restore": 69, "warmup_time": 0.0058171749114990234}
{"loss": -435.2972717285156, "accuracy": 0.5, "time_this_iter_s": 1.025998830795288, "done": false, "timesteps_total": null, "episodes_total": null, "training_iteration": 70, "trial_id": "a0d9a_00357", "experiment_id": "a84899bb77fd4dadab8ef404ea39a6c3", "date": "2023-03-31_17-58-30", "timestamp": 1680278310, "time_total_s": 91.29993724822998, "pid": 1369926, "hostname": "cuda01", "node_ip": "172.29.16.1", "config": {"num_cont": 10, "lf": 0, "temperature": 1, "lr": 1e-06, "alpha": 200, "beta": 4, "seed": 27, "normalized": false, "batch_size": 64}, "time_since_restore": 91.29993724822998, "timesteps_since_restore": 0, "iterations_since_restore": 70, "warmup_time": 0.0058171749114990234}
{"loss": -435.1903076171875, "accuracy": 0.53125, "time_this_iter_s": 1.020824909210205, "done": false, "timesteps_total": null, "episodes_total": null, "training_iteration": 71, "trial_id": "a0d9a_00357", "experiment_id": "a84899bb77fd4dadab8ef404ea39a6c3", "date": "2023-03-31_17-58-31", "timestamp": 1680278311, "time_total_s": 92.32076215744019, "pid": 1369926, "hostname": "cuda01", "node_ip": "172.29.16.1", "config": {"num_cont": 10, "lf": 0, "temperature": 1, "lr": 1e-06, "alpha": 200, "beta": 4, "seed": 27, "normalized": false, "batch_size": 64}, "time_since_restore": 92.32076215744019, "timesteps_since_restore": 0, "iterations_since_restore": 71, "warmup_time": 0.0058171749114990234}
{"loss": -434.86492919921875, "accuracy": 0.40625, "time_this_iter_s": 1.0166151523590088, "done": false, "timesteps_total": null, "episodes_total": null, "training_iteration": 72, "trial_id": "a0d9a_00357", "experiment_id": "a84899bb77fd4dadab8ef404ea39a6c3", "date": "2023-03-31_17-58-32", "timestamp": 1680278312, "time_total_s": 93.3373773097992, "pid": 1369926, "hostname": "cuda01", "node_ip": "172.29.16.1", "config": {"num_cont": 10, "lf": 0, "temperature": 1, "lr": 1e-06, "alpha": 200, "beta": 4, "seed": 27, "normalized": false, "batch_size": 64}, "time_since_restore": 93.3373773097992, "timesteps_since_restore": 0, "iterations_since_restore": 72, "warmup_time": 0.0058171749114990234}
{"loss": -434.968994140625, "accuracy": 0.453125, "time_this_iter_s": 1.0284500122070312, "done": false, "timesteps_total": null, "episodes_total": null, "training_iteration": 73, "trial_id": "a0d9a_00357", "experiment_id": "a84899bb77fd4dadab8ef404ea39a6c3", "date": "2023-03-31_17-58-33", "timestamp": 1680278313, "time_total_s": 94.36582732200623, "pid": 1369926, "hostname": "cuda01", "node_ip": "172.29.16.1", "config": {"num_cont": 10, "lf": 0, "temperature": 1, "lr": 1e-06, "alpha": 200, "beta": 4, "seed": 27, "normalized": false, "batch_size": 64}, "time_since_restore": 94.36582732200623, "timesteps_since_restore": 0, "iterations_since_restore": 73, "warmup_time": 0.0058171749114990234}
{"loss": -434.6235656738281, "accuracy": 0.53125, "time_this_iter_s": 1.2283916473388672, "done": false, "timesteps_total": null, "episodes_total": null, "training_iteration": 74, "trial_id": "a0d9a_00357", "experiment_id": "a84899bb77fd4dadab8ef404ea39a6c3", "date": "2023-03-31_17-58-35", "timestamp": 1680278315, "time_total_s": 95.59421896934509, "pid": 1369926, "hostname": "cuda01", "node_ip": "172.29.16.1", "config": {"num_cont": 10, "lf": 0, "temperature": 1, "lr": 1e-06, "alpha": 200, "beta": 4, "seed": 27, "normalized": false, "batch_size": 64}, "time_since_restore": 95.59421896934509, "timesteps_since_restore": 0, "iterations_since_restore": 74, "warmup_time": 0.0058171749114990234}
{"loss": -434.4541015625, "accuracy": 0.359375, "time_this_iter_s": 1.0279011726379395, "done": false, "timesteps_total": null, "episodes_total": null, "training_iteration": 75, "trial_id": "a0d9a_00357", "experiment_id": "a84899bb77fd4dadab8ef404ea39a6c3", "date": "2023-03-31_17-58-36", "timestamp": 1680278316, "time_total_s": 96.62212014198303, "pid": 1369926, "hostname": "cuda01", "node_ip": "172.29.16.1", "config": {"num_cont": 10, "lf": 0, "temperature": 1, "lr": 1e-06, "alpha": 200, "beta": 4, "seed": 27, "normalized": false, "batch_size": 64}, "time_since_restore": 96.62212014198303, "timesteps_since_restore": 0, "iterations_since_restore": 75, "warmup_time": 0.0058171749114990234}
{"loss": -434.32037353515625, "accuracy": 0.625, "time_this_iter_s": 1.0262691974639893, "done": false, "timesteps_total": null, "episodes_total": null, "training_iteration": 76, "trial_id": "a0d9a_00357", "experiment_id": "a84899bb77fd4dadab8ef404ea39a6c3", "date": "2023-03-31_17-58-37", "timestamp": 1680278317, "time_total_s": 97.64838933944702, "pid": 1369926, "hostname": "cuda01", "node_ip": "172.29.16.1", "config": {"num_cont": 10, "lf": 0, "temperature": 1, "lr": 1e-06, "alpha": 200, "beta": 4, "seed": 27, "normalized": false, "batch_size": 64}, "time_since_restore": 97.64838933944702, "timesteps_since_restore": 0, "iterations_since_restore": 76, "warmup_time": 0.0058171749114990234}
{"loss": -434.2688293457031, "accuracy": 0.515625, "time_this_iter_s": 1.0539484024047852, "done": false, "timesteps_total": null, "episodes_total": null, "training_iteration": 77, "trial_id": "a0d9a_00357", "experiment_id": "a84899bb77fd4dadab8ef404ea39a6c3", "date": "2023-03-31_17-58-38", "timestamp": 1680278318, "time_total_s": 98.7023377418518, "pid": 1369926, "hostname": "cuda01", "node_ip": "172.29.16.1", "config": {"num_cont": 10, "lf": 0, "temperature": 1, "lr": 1e-06, "alpha": 200, "beta": 4, "seed": 27, "normalized": false, "batch_size": 64}, "time_since_restore": 98.7023377418518, "timesteps_since_restore": 0, "iterations_since_restore": 77, "warmup_time": 0.0058171749114990234}
{"loss": -434.0003356933594, "accuracy": 0.609375, "time_this_iter_s": 1.069093942642212, "done": false, "timesteps_total": null, "episodes_total": null, "training_iteration": 78, "trial_id": "a0d9a_00357", "experiment_id": "a84899bb77fd4dadab8ef404ea39a6c3", "date": "2023-03-31_17-58-39", "timestamp": 1680278319, "time_total_s": 99.77143168449402, "pid": 1369926, "hostname": "cuda01", "node_ip": "172.29.16.1", "config": {"num_cont": 10, "lf": 0, "temperature": 1, "lr": 1e-06, "alpha": 200, "beta": 4, "seed": 27, "normalized": false, "batch_size": 64}, "time_since_restore": 99.77143168449402, "timesteps_since_restore": 0, "iterations_since_restore": 78, "warmup_time": 0.0058171749114990234}
{"loss": -433.8258056640625, "accuracy": 0.5, "time_this_iter_s": 1.364487886428833, "done": false, "timesteps_total": null, "episodes_total": null, "training_iteration": 79, "trial_id": "a0d9a_00357", "experiment_id": "a84899bb77fd4dadab8ef404ea39a6c3", "date": "2023-03-31_17-58-40", "timestamp": 1680278320, "time_total_s": 101.13591957092285, "pid": 1369926, "hostname": "cuda01", "node_ip": "172.29.16.1", "config": {"num_cont": 10, "lf": 0, "temperature": 1, "lr": 1e-06, "alpha": 200, "beta": 4, "seed": 27, "normalized": false, "batch_size": 64}, "time_since_restore": 101.13591957092285, "timesteps_since_restore": 0, "iterations_since_restore": 79, "warmup_time": 0.0058171749114990234}
{"loss": -433.5928649902344, "accuracy": 0.65625, "time_this_iter_s": 1.047773838043213, "done": false, "timesteps_total": null, "episodes_total": null, "training_iteration": 80, "trial_id": "a0d9a_00357", "experiment_id": "a84899bb77fd4dadab8ef404ea39a6c3", "date": "2023-03-31_17-58-41", "timestamp": 1680278321, "time_total_s": 102.18369340896606, "pid": 1369926, "hostname": "cuda01", "node_ip": "172.29.16.1", "config": {"num_cont": 10, "lf": 0, "temperature": 1, "lr": 1e-06, "alpha": 200, "beta": 4, "seed": 27, "normalized": false, "batch_size": 64}, "time_since_restore": 102.18369340896606, "timesteps_since_restore": 0, "iterations_since_restore": 80, "warmup_time": 0.0058171749114990234}
{"loss": -433.4859313964844, "accuracy": 0.578125, "time_this_iter_s": 1.1106340885162354, "done": false, "timesteps_total": null, "episodes_total": null, "training_iteration": 81, "trial_id": "a0d9a_00357", "experiment_id": "a84899bb77fd4dadab8ef404ea39a6c3", "date": "2023-03-31_17-58-42", "timestamp": 1680278322, "time_total_s": 103.2943274974823, "pid": 1369926, "hostname": "cuda01", "node_ip": "172.29.16.1", "config": {"num_cont": 10, "lf": 0, "temperature": 1, "lr": 1e-06, "alpha": 200, "beta": 4, "seed": 27, "normalized": false, "batch_size": 64}, "time_since_restore": 103.2943274974823, "timesteps_since_restore": 0, "iterations_since_restore": 81, "warmup_time": 0.0058171749114990234}
{"loss": -433.34088134765625, "accuracy": 0.546875, "time_this_iter_s": 1.0428516864776611, "done": false, "timesteps_total": null, "episodes_total": null, "training_iteration": 82, "trial_id": "a0d9a_00357", "experiment_id": "a84899bb77fd4dadab8ef404ea39a6c3", "date": "2023-03-31_17-58-43", "timestamp": 1680278323, "time_total_s": 104.33717918395996, "pid": 1369926, "hostname": "cuda01", "node_ip": "172.29.16.1", "config": {"num_cont": 10, "lf": 0, "temperature": 1, "lr": 1e-06, "alpha": 200, "beta": 4, "seed": 27, "normalized": false, "batch_size": 64}, "time_since_restore": 104.33717918395996, "timesteps_since_restore": 0, "iterations_since_restore": 82, "warmup_time": 0.0058171749114990234}
{"loss": -433.1205749511719, "accuracy": 0.4375, "time_this_iter_s": 1.0158922672271729, "done": false, "timesteps_total": null, "episodes_total": null, "training_iteration": 83, "trial_id": "a0d9a_00357", "experiment_id": "a84899bb77fd4dadab8ef404ea39a6c3", "date": "2023-03-31_17-58-44", "timestamp": 1680278324, "time_total_s": 105.35307145118713, "pid": 1369926, "hostname": "cuda01", "node_ip": "172.29.16.1", "config": {"num_cont": 10, "lf": 0, "temperature": 1, "lr": 1e-06, "alpha": 200, "beta": 4, "seed": 27, "normalized": false, "batch_size": 64}, "time_since_restore": 105.35307145118713, "timesteps_since_restore": 0, "iterations_since_restore": 83, "warmup_time": 0.0058171749114990234}
{"loss": -432.8941650390625, "accuracy": 0.65625, "time_this_iter_s": 7.834477186203003, "done": false, "timesteps_total": null, "episodes_total": null, "training_iteration": 84, "trial_id": "a0d9a_00357", "experiment_id": "a84899bb77fd4dadab8ef404ea39a6c3", "date": "2023-03-31_17-58-52", "timestamp": 1680278332, "time_total_s": 113.18754863739014, "pid": 1369926, "hostname": "cuda01", "node_ip": "172.29.16.1", "config": {"num_cont": 10, "lf": 0, "temperature": 1, "lr": 1e-06, "alpha": 200, "beta": 4, "seed": 27, "normalized": false, "batch_size": 64}, "time_since_restore": 113.18754863739014, "timesteps_since_restore": 0, "iterations_since_restore": 84, "warmup_time": 0.0058171749114990234}
{"loss": -432.6910400390625, "accuracy": 0.515625, "time_this_iter_s": 1.6639299392700195, "done": false, "timesteps_total": null, "episodes_total": null, "training_iteration": 85, "trial_id": "a0d9a_00357", "experiment_id": "a84899bb77fd4dadab8ef404ea39a6c3", "date": "2023-03-31_17-58-54", "timestamp": 1680278334, "time_total_s": 114.85147857666016, "pid": 1369926, "hostname": "cuda01", "node_ip": "172.29.16.1", "config": {"num_cont": 10, "lf": 0, "temperature": 1, "lr": 1e-06, "alpha": 200, "beta": 4, "seed": 27, "normalized": false, "batch_size": 64}, "time_since_restore": 114.85147857666016, "timesteps_since_restore": 0, "iterations_since_restore": 85, "warmup_time": 0.0058171749114990234}
{"loss": -432.5064697265625, "accuracy": 0.546875, "time_this_iter_s": 1.083242416381836, "done": false, "timesteps_total": null, "episodes_total": null, "training_iteration": 86, "trial_id": "a0d9a_00357", "experiment_id": "a84899bb77fd4dadab8ef404ea39a6c3", "date": "2023-03-31_17-58-55", "timestamp": 1680278335, "time_total_s": 115.93472099304199, "pid": 1369926, "hostname": "cuda01", "node_ip": "172.29.16.1", "config": {"num_cont": 10, "lf": 0, "temperature": 1, "lr": 1e-06, "alpha": 200, "beta": 4, "seed": 27, "normalized": false, "batch_size": 64}, "time_since_restore": 115.93472099304199, "timesteps_since_restore": 0, "iterations_since_restore": 86, "warmup_time": 0.0058171749114990234}
{"loss": -432.46697998046875, "accuracy": 0.4375, "time_this_iter_s": 1.080561637878418, "done": false, "timesteps_total": null, "episodes_total": null, "training_iteration": 87, "trial_id": "a0d9a_00357", "experiment_id": "a84899bb77fd4dadab8ef404ea39a6c3", "date": "2023-03-31_17-58-56", "timestamp": 1680278336, "time_total_s": 117.01528263092041, "pid": 1369926, "hostname": "cuda01", "node_ip": "172.29.16.1", "config": {"num_cont": 10, "lf": 0, "temperature": 1, "lr": 1e-06, "alpha": 200, "beta": 4, "seed": 27, "normalized": false, "batch_size": 64}, "time_since_restore": 117.01528263092041, "timesteps_since_restore": 0, "iterations_since_restore": 87, "warmup_time": 0.0058171749114990234}
{"loss": -432.2411804199219, "accuracy": 0.5, "time_this_iter_s": 1.0866827964782715, "done": false, "timesteps_total": null, "episodes_total": null, "training_iteration": 88, "trial_id": "a0d9a_00357", "experiment_id": "a84899bb77fd4dadab8ef404ea39a6c3", "date": "2023-03-31_17-58-57", "timestamp": 1680278337, "time_total_s": 118.10196542739868, "pid": 1369926, "hostname": "cuda01", "node_ip": "172.29.16.1", "config": {"num_cont": 10, "lf": 0, "temperature": 1, "lr": 1e-06, "alpha": 200, "beta": 4, "seed": 27, "normalized": false, "batch_size": 64}, "time_since_restore": 118.10196542739868, "timesteps_since_restore": 0, "iterations_since_restore": 88, "warmup_time": 0.0058171749114990234}
{"loss": -432.0849609375, "accuracy": 0.484375, "time_this_iter_s": 1.2138636112213135, "done": false, "timesteps_total": null, "episodes_total": null, "training_iteration": 89, "trial_id": "a0d9a_00357", "experiment_id": "a84899bb77fd4dadab8ef404ea39a6c3", "date": "2023-03-31_17-58-58", "timestamp": 1680278338, "time_total_s": 119.31582903862, "pid": 1369926, "hostname": "cuda01", "node_ip": "172.29.16.1", "config": {"num_cont": 10, "lf": 0, "temperature": 1, "lr": 1e-06, "alpha": 200, "beta": 4, "seed": 27, "normalized": false, "batch_size": 64}, "time_since_restore": 119.31582903862, "timesteps_since_restore": 0, "iterations_since_restore": 89, "warmup_time": 0.0058171749114990234}
{"loss": -431.7566833496094, "accuracy": 0.515625, "time_this_iter_s": 1.0460014343261719, "done": false, "timesteps_total": null, "episodes_total": null, "training_iteration": 90, "trial_id": "a0d9a_00357", "experiment_id": "a84899bb77fd4dadab8ef404ea39a6c3", "date": "2023-03-31_17-58-59", "timestamp": 1680278339, "time_total_s": 120.36183047294617, "pid": 1369926, "hostname": "cuda01", "node_ip": "172.29.16.1", "config": {"num_cont": 10, "lf": 0, "temperature": 1, "lr": 1e-06, "alpha": 200, "beta": 4, "seed": 27, "normalized": false, "batch_size": 64}, "time_since_restore": 120.36183047294617, "timesteps_since_restore": 0, "iterations_since_restore": 90, "warmup_time": 0.0058171749114990234}
{"loss": -431.6455993652344, "accuracy": 0.453125, "time_this_iter_s": 1.1834025382995605, "done": false, "timesteps_total": null, "episodes_total": null, "training_iteration": 91, "trial_id": "a0d9a_00357", "experiment_id": "a84899bb77fd4dadab8ef404ea39a6c3", "date": "2023-03-31_17-59-01", "timestamp": 1680278341, "time_total_s": 121.54523301124573, "pid": 1369926, "hostname": "cuda01", "node_ip": "172.29.16.1", "config": {"num_cont": 10, "lf": 0, "temperature": 1, "lr": 1e-06, "alpha": 200, "beta": 4, "seed": 27, "normalized": false, "batch_size": 64}, "time_since_restore": 121.54523301124573, "timesteps_since_restore": 0, "iterations_since_restore": 91, "warmup_time": 0.0058171749114990234}
{"loss": -431.3010559082031, "accuracy": 0.546875, "time_this_iter_s": 1.065565586090088, "done": false, "timesteps_total": null, "episodes_total": null, "training_iteration": 92, "trial_id": "a0d9a_00357", "experiment_id": "a84899bb77fd4dadab8ef404ea39a6c3", "date": "2023-03-31_17-59-02", "timestamp": 1680278342, "time_total_s": 122.61079859733582, "pid": 1369926, "hostname": "cuda01", "node_ip": "172.29.16.1", "config": {"num_cont": 10, "lf": 0, "temperature": 1, "lr": 1e-06, "alpha": 200, "beta": 4, "seed": 27, "normalized": false, "batch_size": 64}, "time_since_restore": 122.61079859733582, "timesteps_since_restore": 0, "iterations_since_restore": 92, "warmup_time": 0.0058171749114990234}
{"loss": -431.22198486328125, "accuracy": 0.4375, "time_this_iter_s": 1.0438861846923828, "done": false, "timesteps_total": null, "episodes_total": null, "training_iteration": 93, "trial_id": "a0d9a_00357", "experiment_id": "a84899bb77fd4dadab8ef404ea39a6c3", "date": "2023-03-31_17-59-03", "timestamp": 1680278343, "time_total_s": 123.6546847820282, "pid": 1369926, "hostname": "cuda01", "node_ip": "172.29.16.1", "config": {"num_cont": 10, "lf": 0, "temperature": 1, "lr": 1e-06, "alpha": 200, "beta": 4, "seed": 27, "normalized": false, "batch_size": 64}, "time_since_restore": 123.6546847820282, "timesteps_since_restore": 0, "iterations_since_restore": 93, "warmup_time": 0.0058171749114990234}
{"loss": -430.76275634765625, "accuracy": 0.640625, "time_this_iter_s": 1.2372324466705322, "done": false, "timesteps_total": null, "episodes_total": null, "training_iteration": 94, "trial_id": "a0d9a_00357", "experiment_id": "a84899bb77fd4dadab8ef404ea39a6c3", "date": "2023-03-31_17-59-04", "timestamp": 1680278344, "time_total_s": 124.89191722869873, "pid": 1369926, "hostname": "cuda01", "node_ip": "172.29.16.1", "config": {"num_cont": 10, "lf": 0, "temperature": 1, "lr": 1e-06, "alpha": 200, "beta": 4, "seed": 27, "normalized": false, "batch_size": 64}, "time_since_restore": 124.89191722869873, "timesteps_since_restore": 0, "iterations_since_restore": 94, "warmup_time": 0.0058171749114990234}
{"loss": -430.8894958496094, "accuracy": 0.453125, "time_this_iter_s": 1.059643268585205, "done": false, "timesteps_total": null, "episodes_total": null, "training_iteration": 95, "trial_id": "a0d9a_00357", "experiment_id": "a84899bb77fd4dadab8ef404ea39a6c3", "date": "2023-03-31_17-59-05", "timestamp": 1680278345, "time_total_s": 125.95156049728394, "pid": 1369926, "hostname": "cuda01", "node_ip": "172.29.16.1", "config": {"num_cont": 10, "lf": 0, "temperature": 1, "lr": 1e-06, "alpha": 200, "beta": 4, "seed": 27, "normalized": false, "batch_size": 64}, "time_since_restore": 125.95156049728394, "timesteps_since_restore": 0, "iterations_since_restore": 95, "warmup_time": 0.0058171749114990234}
{"loss": -430.36480712890625, "accuracy": 0.5625, "time_this_iter_s": 1.0578010082244873, "done": false, "timesteps_total": null, "episodes_total": null, "training_iteration": 96, "trial_id": "a0d9a_00357", "experiment_id": "a84899bb77fd4dadab8ef404ea39a6c3", "date": "2023-03-31_17-59-06", "timestamp": 1680278346, "time_total_s": 127.00936150550842, "pid": 1369926, "hostname": "cuda01", "node_ip": "172.29.16.1", "config": {"num_cont": 10, "lf": 0, "temperature": 1, "lr": 1e-06, "alpha": 200, "beta": 4, "seed": 27, "normalized": false, "batch_size": 64}, "time_since_restore": 127.00936150550842, "timesteps_since_restore": 0, "iterations_since_restore": 96, "warmup_time": 0.0058171749114990234}
{"loss": -430.3178405761719, "accuracy": 0.484375, "time_this_iter_s": 1.0815696716308594, "done": false, "timesteps_total": null, "episodes_total": null, "training_iteration": 97, "trial_id": "a0d9a_00357", "experiment_id": "a84899bb77fd4dadab8ef404ea39a6c3", "date": "2023-03-31_17-59-07", "timestamp": 1680278347, "time_total_s": 128.09093117713928, "pid": 1369926, "hostname": "cuda01", "node_ip": "172.29.16.1", "config": {"num_cont": 10, "lf": 0, "temperature": 1, "lr": 1e-06, "alpha": 200, "beta": 4, "seed": 27, "normalized": false, "batch_size": 64}, "time_since_restore": 128.09093117713928, "timesteps_since_restore": 0, "iterations_since_restore": 97, "warmup_time": 0.0058171749114990234}
{"loss": -429.82073974609375, "accuracy": 0.46875, "time_this_iter_s": 1.04593825340271, "done": false, "timesteps_total": null, "episodes_total": null, "training_iteration": 98, "trial_id": "a0d9a_00357", "experiment_id": "a84899bb77fd4dadab8ef404ea39a6c3", "date": "2023-03-31_17-59-08", "timestamp": 1680278348, "time_total_s": 129.136869430542, "pid": 1369926, "hostname": "cuda01", "node_ip": "172.29.16.1", "config": {"num_cont": 10, "lf": 0, "temperature": 1, "lr": 1e-06, "alpha": 200, "beta": 4, "seed": 27, "normalized": false, "batch_size": 64}, "time_since_restore": 129.136869430542, "timesteps_since_restore": 0, "iterations_since_restore": 98, "warmup_time": 0.0058171749114990234}
{"loss": -429.7492370605469, "accuracy": 0.46875, "time_this_iter_s": 1.141535997390747, "done": false, "timesteps_total": null, "episodes_total": null, "training_iteration": 99, "trial_id": "a0d9a_00357", "experiment_id": "a84899bb77fd4dadab8ef404ea39a6c3", "date": "2023-03-31_17-59-09", "timestamp": 1680278349, "time_total_s": 130.27840542793274, "pid": 1369926, "hostname": "cuda01", "node_ip": "172.29.16.1", "config": {"num_cont": 10, "lf": 0, "temperature": 1, "lr": 1e-06, "alpha": 200, "beta": 4, "seed": 27, "normalized": false, "batch_size": 64}, "time_since_restore": 130.27840542793274, "timesteps_since_restore": 0, "iterations_since_restore": 99, "warmup_time": 0.0058171749114990234}
{"loss": -429.42803955078125, "accuracy": 0.59375, "time_this_iter_s": 1.0702853202819824, "done": true, "timesteps_total": null, "episodes_total": null, "training_iteration": 100, "trial_id": "a0d9a_00357", "experiment_id": "a84899bb77fd4dadab8ef404ea39a6c3", "date": "2023-03-31_17-59-10", "timestamp": 1680278350, "time_total_s": 131.34869074821472, "pid": 1369926, "hostname": "cuda01", "node_ip": "172.29.16.1", "config": {"num_cont": 10, "lf": 0, "temperature": 1, "lr": 1e-06, "alpha": 200, "beta": 4, "seed": 27, "normalized": false, "batch_size": 64}, "time_since_restore": 131.34869074821472, "timesteps_since_restore": 0, "iterations_since_restore": 100, "warmup_time": 0.0058171749114990234}
